{
"meta":{"test_sets":[],"test_metrics":[],"learn_metrics":[{"best_value":"Min","name":"RMSE"}],"launch_mode":"Train","parameters":"","iteration_count":1000,"learn_sets":["learn"],"name":"experiment"},
"iterations":[
{"learn":[14.61268541],"iteration":0,"passed_time":0.1379738861,"remaining_time":137.8359122},
{"learn":[14.23196558],"iteration":1,"passed_time":0.1395078512,"remaining_time":69.61441773},
{"learn":[13.86674177],"iteration":2,"passed_time":0.1409653149,"remaining_time":46.84747299},
{"learn":[13.49946468],"iteration":3,"passed_time":0.1423685466,"remaining_time":35.44976811},
{"learn":[13.16661202],"iteration":4,"passed_time":0.1436219171,"remaining_time":28.58076151},
{"learn":[12.85632158],"iteration":5,"passed_time":0.1447783952,"remaining_time":23.98495414},
{"learn":[12.56784336],"iteration":6,"passed_time":0.1460268125,"remaining_time":20.7149464},
{"learn":[12.31617801],"iteration":7,"passed_time":0.1472132238,"remaining_time":18.25443976},
{"learn":[12.01509946],"iteration":8,"passed_time":0.1483732983,"remaining_time":16.33754874},
{"learn":[11.71512571],"iteration":9,"passed_time":0.1496244048,"remaining_time":14.81281608},
{"learn":[11.43264457],"iteration":10,"passed_time":0.150771907,"remaining_time":13.55576509},
{"learn":[11.17973129],"iteration":11,"passed_time":0.1520754768,"remaining_time":12.52088092},
{"learn":[10.93746433],"iteration":12,"passed_time":0.1536654063,"remaining_time":11.66675046},
{"learn":[10.69387075],"iteration":13,"passed_time":0.1549527573,"remaining_time":10.91310134},
{"learn":[10.4615922],"iteration":14,"passed_time":0.1563639387,"remaining_time":10.26789864},
{"learn":[10.2299235],"iteration":15,"passed_time":0.1576418529,"remaining_time":9.694973952},
{"learn":[10.01419731],"iteration":16,"passed_time":0.158912414,"remaining_time":9.188876645},
{"learn":[9.795856918],"iteration":17,"passed_time":0.1602818659,"remaining_time":8.744266241},
{"learn":[9.60040151],"iteration":18,"passed_time":0.1615343849,"remaining_time":8.340275349},
{"learn":[9.418664989],"iteration":19,"passed_time":0.1629145111,"remaining_time":7.982811041},
{"learn":[9.249278645],"iteration":20,"passed_time":0.1643419666,"remaining_time":7.661465965},
{"learn":[9.090113396],"iteration":21,"passed_time":0.1655635505,"remaining_time":7.360052382},
{"learn":[8.909548708],"iteration":22,"passed_time":0.166790484,"remaining_time":7.08496969},
{"learn":[8.740140208],"iteration":23,"passed_time":0.1680140415,"remaining_time":6.83257102},
{"learn":[8.59377682],"iteration":24,"passed_time":0.1691496424,"remaining_time":6.596836054},
{"learn":[8.453885414],"iteration":25,"passed_time":0.1702820677,"remaining_time":6.379028229},
{"learn":[8.317732234],"iteration":26,"passed_time":0.1713813139,"remaining_time":6.176074758},
{"learn":[8.180896085],"iteration":27,"passed_time":0.1725427108,"remaining_time":5.989696961},
{"learn":[8.053220863],"iteration":28,"passed_time":0.1736873378,"remaining_time":5.815531207},
{"learn":[7.924234474],"iteration":29,"passed_time":0.1748190017,"remaining_time":5.652481056},
{"learn":[7.818879511],"iteration":30,"passed_time":0.1759743077,"remaining_time":5.500616265},
{"learn":[7.719346395],"iteration":31,"passed_time":0.1770300466,"remaining_time":5.355158909},
{"learn":[7.624163594],"iteration":32,"passed_time":0.1782182912,"remaining_time":5.222335987},
{"learn":[7.524952543],"iteration":33,"passed_time":0.1793624674,"remaining_time":5.096004221},
{"learn":[7.424464745],"iteration":34,"passed_time":0.1805716393,"remaining_time":4.978618054},
{"learn":[7.327482321],"iteration":35,"passed_time":0.1816820854,"remaining_time":4.86504251},
{"learn":[7.238666841],"iteration":36,"passed_time":0.1827321041,"remaining_time":4.755973412},
{"learn":[7.158842395],"iteration":37,"passed_time":0.1839370184,"remaining_time":4.656510834},
{"learn":[7.074348246],"iteration":38,"passed_time":0.1851004388,"remaining_time":4.561064659},
{"learn":[6.992269093],"iteration":39,"passed_time":0.1861927628,"remaining_time":4.468626306},
{"learn":[6.925219745],"iteration":40,"passed_time":0.1872612543,"remaining_time":4.380086411},
{"learn":[6.86013671],"iteration":41,"passed_time":0.1888780015,"remaining_time":4.308217272},
{"learn":[6.786739622],"iteration":42,"passed_time":0.1905490854,"remaining_time":4.240824993},
{"learn":[6.73057926],"iteration":43,"passed_time":0.1918782308,"remaining_time":4.16899065},
{"learn":[6.666356486],"iteration":44,"passed_time":0.1931140901,"remaining_time":4.098310135},
{"learn":[6.606182832],"iteration":45,"passed_time":0.194237289,"remaining_time":4.028312472},
{"learn":[6.547854615],"iteration":46,"passed_time":0.1954178199,"remaining_time":3.962408135},
{"learn":[6.49240675],"iteration":47,"passed_time":0.1965749191,"remaining_time":3.898735895},
{"learn":[6.431317261],"iteration":48,"passed_time":0.1977334108,"remaining_time":3.837642319},
{"learn":[6.377586395],"iteration":49,"passed_time":0.198939407,"remaining_time":3.779848733},
{"learn":[6.327558015],"iteration":50,"passed_time":0.2000327628,"remaining_time":3.722178272},
{"learn":[6.282040317],"iteration":51,"passed_time":0.2011668811,"remaining_time":3.667426985},
{"learn":[6.237655841],"iteration":52,"passed_time":0.2028472314,"remaining_time":3.624459022},
{"learn":[6.192792003],"iteration":53,"passed_time":0.2043885043,"remaining_time":3.580583798},
{"learn":[6.150579347],"iteration":54,"passed_time":0.2057890969,"remaining_time":3.535830846},
{"learn":[6.115693845],"iteration":55,"passed_time":0.2069541703,"remaining_time":3.488656013},
{"learn":[6.078780782],"iteration":56,"passed_time":0.2082091236,"remaining_time":3.444582519},
{"learn":[6.045146957],"iteration":57,"passed_time":0.2094092794,"remaining_time":3.401095538},
{"learn":[6.008080327],"iteration":58,"passed_time":0.2104808664,"remaining_time":3.356991446},
{"learn":[5.977575734],"iteration":59,"passed_time":0.2115671496,"remaining_time":3.314552011},
{"learn":[5.948036502],"iteration":60,"passed_time":0.2126971506,"remaining_time":3.274141384},
{"learn":[5.914888282],"iteration":61,"passed_time":0.2137555742,"remaining_time":3.233914977},
{"learn":[5.884957796],"iteration":62,"passed_time":0.2148951723,"remaining_time":3.196139308},
{"learn":[5.849539885],"iteration":63,"passed_time":0.2160975821,"remaining_time":3.160427138},
{"learn":[5.821387627],"iteration":64,"passed_time":0.2172831267,"remaining_time":3.125534208},
{"learn":[5.797012279],"iteration":65,"passed_time":0.2184038011,"remaining_time":3.090744701},
{"learn":[5.768685095],"iteration":66,"passed_time":0.2195586563,"remaining_time":3.057436214},
{"learn":[5.755484587],"iteration":67,"passed_time":0.2202380606,"remaining_time":3.018556948},
{"learn":[5.731887055],"iteration":68,"passed_time":0.2212985378,"remaining_time":2.985926648},
{"learn":[5.707148487],"iteration":69,"passed_time":0.2223959308,"remaining_time":2.954688795},
{"learn":[5.685365039],"iteration":70,"passed_time":0.2235114159,"remaining_time":2.924536696},
{"learn":[5.663541834],"iteration":71,"passed_time":0.2248593893,"remaining_time":2.898187684},
{"learn":[5.638108797],"iteration":72,"passed_time":0.2261462895,"remaining_time":2.871748087},
{"learn":[5.619204893],"iteration":73,"passed_time":0.2273779414,"remaining_time":2.845296942},
{"learn":[5.598472793],"iteration":74,"passed_time":0.2286143217,"remaining_time":2.819576634},
{"learn":[5.577007075],"iteration":75,"passed_time":0.2298078056,"remaining_time":2.79397911},
{"learn":[5.562637084],"iteration":76,"passed_time":0.2312992954,"remaining_time":2.772587658},
{"learn":[5.54729991],"iteration":77,"passed_time":0.2324567352,"remaining_time":2.747757819},
{"learn":[5.530737623],"iteration":78,"passed_time":0.2335754461,"remaining_time":2.723075771},
{"learn":[5.513704873],"iteration":79,"passed_time":0.2346977835,"remaining_time":2.69902451},
{"learn":[5.501575529],"iteration":80,"passed_time":0.2358261615,"remaining_time":2.675607932},
{"learn":[5.484080734],"iteration":81,"passed_time":0.2368304087,"remaining_time":2.651345307},
{"learn":[5.472178894],"iteration":82,"passed_time":0.2379564226,"remaining_time":2.628988428},
{"learn":[5.458923342],"iteration":83,"passed_time":0.2392117266,"remaining_time":2.608546923},
{"learn":[5.451382371],"iteration":84,"passed_time":0.2401501666,"remaining_time":2.585145912},
{"learn":[5.441410748],"iteration":85,"passed_time":0.241485453,"remaining_time":2.56648493},
{"learn":[5.434047468],"iteration":86,"passed_time":0.2423982273,"remaining_time":2.543788294},
{"learn":[5.422107497],"iteration":87,"passed_time":0.2436319128,"remaining_time":2.524912551},
{"learn":[5.40731265],"iteration":88,"passed_time":0.2447999816,"remaining_time":2.505761609},
{"learn":[5.396360181],"iteration":89,"passed_time":0.2459204255,"remaining_time":2.486528747},
{"learn":[5.383793239],"iteration":90,"passed_time":0.2469906802,"remaining_time":2.467192619},
{"learn":[5.369605034],"iteration":91,"passed_time":0.2482320794,"remaining_time":2.449942697},
{"learn":[5.357467333],"iteration":92,"passed_time":0.2496521414,"remaining_time":2.434779487},
{"learn":[5.341109968],"iteration":93,"passed_time":0.2510067521,"remaining_time":2.419277845},
{"learn":[5.330529276],"iteration":94,"passed_time":0.2522773284,"remaining_time":2.403273497},
{"learn":[5.319862075],"iteration":95,"passed_time":0.2535296571,"remaining_time":2.387404271},
{"learn":[5.313052243],"iteration":96,"passed_time":0.2546433991,"remaining_time":2.370546283},
{"learn":[5.299677207],"iteration":97,"passed_time":0.2557489366,"remaining_time":2.35393409},
{"learn":[5.287546698],"iteration":98,"passed_time":0.2570533079,"remaining_time":2.339444752},
{"learn":[5.279803754],"iteration":99,"passed_time":0.2582501077,"remaining_time":2.32425097},
{"learn":[5.272254612],"iteration":100,"passed_time":0.2597760979,"remaining_time":2.312264475},
{"learn":[5.268813888],"iteration":101,"passed_time":0.2604786181,"remaining_time":2.293233324},
{"learn":[5.258113767],"iteration":102,"passed_time":0.2617006028,"remaining_time":2.279081949},
{"learn":[5.251018576],"iteration":103,"passed_time":0.2628710461,"remaining_time":2.264735166},
{"learn":[5.24171237],"iteration":104,"passed_time":0.2640506854,"remaining_time":2.250717747},
{"learn":[5.233984943],"iteration":105,"passed_time":0.2652369165,"remaining_time":2.236998144},
{"learn":[5.226240449],"iteration":106,"passed_time":0.2665191584,"remaining_time":2.224314097},
{"learn":[5.220541644],"iteration":107,"passed_time":0.2677636331,"remaining_time":2.211529266},
{"learn":[5.211712096],"iteration":108,"passed_time":0.2690092698,"remaining_time":2.198965683},
{"learn":[5.203388597],"iteration":109,"passed_time":0.2702622597,"remaining_time":2.186667374},
{"learn":[5.196026544],"iteration":110,"passed_time":0.2712999564,"remaining_time":2.172843795},
{"learn":[5.188716772],"iteration":111,"passed_time":0.2724570957,"remaining_time":2.160195544},
{"learn":[5.182163132],"iteration":112,"passed_time":0.2736277991,"remaining_time":2.147857148},
{"learn":[5.17764747],"iteration":113,"passed_time":0.2749517151,"remaining_time":2.136905435},
{"learn":[5.170548056],"iteration":114,"passed_time":0.2760900409,"remaining_time":2.124692924},
{"learn":[5.165901827],"iteration":115,"passed_time":0.2770615599,"remaining_time":2.111400163},
{"learn":[5.160333668],"iteration":116,"passed_time":0.2782697801,"remaining_time":2.100104408},
{"learn":[5.148953243],"iteration":117,"passed_time":0.2794956817,"remaining_time":2.08911179},
{"learn":[5.144729126],"iteration":118,"passed_time":0.2803964347,"remaining_time":2.075876126},
{"learn":[5.139939946],"iteration":119,"passed_time":0.2815220779,"remaining_time":2.064495238},
{"learn":[5.132898872],"iteration":120,"passed_time":0.2827295668,"remaining_time":2.053878423},
{"learn":[5.129073077],"iteration":121,"passed_time":0.2839495476,"remaining_time":2.04350576},
{"learn":[5.127123916],"iteration":122,"passed_time":0.2846297481,"remaining_time":2.029433244},
{"learn":[5.121282057],"iteration":123,"passed_time":0.285805781,"remaining_time":2.019079549},
{"learn":[5.114489821],"iteration":124,"passed_time":0.2868616801,"remaining_time":2.00803176},
{"learn":[5.107777291],"iteration":125,"passed_time":0.2880651974,"remaining_time":1.998166528},
{"learn":[5.103518754],"iteration":126,"passed_time":0.2893297077,"remaining_time":1.988856967},
{"learn":[5.101133351],"iteration":127,"passed_time":0.2901340892,"remaining_time":1.976538483},
{"learn":[5.096462705],"iteration":128,"passed_time":0.2913901546,"remaining_time":1.967448253},
{"learn":[5.08562082],"iteration":129,"passed_time":0.2926994045,"remaining_time":1.958834476},
{"learn":[5.080483682],"iteration":130,"passed_time":0.2938047416,"remaining_time":1.948979546},
{"learn":[5.07437499],"iteration":131,"passed_time":0.2951907129,"remaining_time":1.941102567},
{"learn":[5.070683732],"iteration":132,"passed_time":0.2964800675,"remaining_time":1.932693372},
{"learn":[5.06432037],"iteration":133,"passed_time":0.2978353694,"remaining_time":1.924816641},
{"learn":[5.057436484],"iteration":134,"passed_time":0.2991564902,"remaining_time":1.916817511},
{"learn":[5.053254656],"iteration":135,"passed_time":0.3003035014,"remaining_time":1.90781048},
{"learn":[5.04801663],"iteration":136,"passed_time":0.3014482186,"remaining_time":1.898903742},
{"learn":[5.045680836],"iteration":137,"passed_time":0.3025071835,"remaining_time":1.889573856},
{"learn":[5.041857933],"iteration":138,"passed_time":0.3039722763,"remaining_time":1.882878633},
{"learn":[5.035264888],"iteration":139,"passed_time":0.305270116,"remaining_time":1.875230713},
{"learn":[5.028771948],"iteration":140,"passed_time":0.3064408194,"remaining_time":1.866898325},
{"learn":[5.024912247],"iteration":141,"passed_time":0.3076899925,"remaining_time":1.85914094},
{"learn":[5.02239068],"iteration":142,"passed_time":0.3089184086,"remaining_time":1.851350183},
{"learn":[5.017110572],"iteration":143,"passed_time":0.3106207778,"remaining_time":1.846467957},
{"learn":[5.010707886],"iteration":144,"passed_time":0.3121679011,"remaining_time":1.840714176},
{"learn":[5.004389868],"iteration":145,"passed_time":0.3135919153,"remaining_time":1.834297916},
{"learn":[4.997628683],"iteration":146,"passed_time":0.314813624,"remaining_time":1.826775655},
{"learn":[4.991497851],"iteration":147,"passed_time":0.3160511563,"remaining_time":1.81942963},
{"learn":[4.988345253],"iteration":148,"passed_time":0.3172504306,"remaining_time":1.81194709},
{"learn":[4.98460423],"iteration":149,"passed_time":0.3184063577,"remaining_time":1.804302694},
{"learn":[4.982441783],"iteration":150,"passed_time":0.3196023164,"remaining_time":1.796969316},
{"learn":[4.977461771],"iteration":151,"passed_time":0.320875923,"remaining_time":1.790149886},
{"learn":[4.973601586],"iteration":152,"passed_time":0.3222005603,"remaining_time":1.783685455},
{"learn":[4.968328804],"iteration":153,"passed_time":0.3236103789,"remaining_time":1.777755718},
{"learn":[4.9640736],"iteration":154,"passed_time":0.3251206269,"remaining_time":1.772431805},
{"learn":[4.960865882],"iteration":155,"passed_time":0.3264424489,"remaining_time":1.766137352},
{"learn":[4.957014156],"iteration":156,"passed_time":0.327730381,"remaining_time":1.759724275},
{"learn":[4.952244852],"iteration":157,"passed_time":0.3288618946,"remaining_time":1.752542502},
{"learn":[4.949695675],"iteration":158,"passed_time":0.3299352849,"remaining_time":1.7451294},
{"learn":[4.946584698],"iteration":159,"passed_time":0.3310573966,"remaining_time":1.738051332},
{"learn":[4.940192834],"iteration":160,"passed_time":0.3321813068,"remaining_time":1.731056624},
{"learn":[4.936727994],"iteration":161,"passed_time":0.3332729395,"remaining_time":1.723967428},
{"learn":[4.932342063],"iteration":162,"passed_time":0.3343107364,"remaining_time":1.716675376},
{"learn":[4.925830838],"iteration":163,"passed_time":0.3354526986,"remaining_time":1.709990586},
{"learn":[4.922571773],"iteration":164,"passed_time":0.3366189942,"remaining_time":1.703496122},
{"learn":[4.918395814],"iteration":165,"passed_time":0.3376850514,"remaining_time":1.696562246},
{"learn":[4.911142452],"iteration":166,"passed_time":0.3387353205,"remaining_time":1.689619892},
{"learn":[4.908276131],"iteration":167,"passed_time":0.3398309703,"remaining_time":1.682972424},
{"learn":[4.904584645],"iteration":168,"passed_time":0.34098272,"remaining_time":1.676666511},
{"learn":[4.89795517],"iteration":169,"passed_time":0.341987408,"remaining_time":1.669703227},
{"learn":[4.895556491],"iteration":170,"passed_time":0.3430800524,"remaining_time":1.663236044},
{"learn":[4.890591233],"iteration":171,"passed_time":0.3441959684,"remaining_time":1.656943383},
{"learn":[4.884629277],"iteration":172,"passed_time":0.3452513465,"remaining_time":1.650421177},
{"learn":[4.880550786],"iteration":173,"passed_time":0.3463842627,"remaining_time":1.644329891},
{"learn":[4.876384842],"iteration":174,"passed_time":0.3474286112,"remaining_time":1.637877739},
{"learn":[4.872638238],"iteration":175,"passed_time":0.3485743955,"remaining_time":1.631961942},
{"learn":[4.869137118],"iteration":176,"passed_time":0.3497224185,"remaining_time":1.626110455},
{"learn":[4.863587157],"iteration":177,"passed_time":0.350833055,"remaining_time":1.620139164},
{"learn":[4.858028614],"iteration":178,"passed_time":0.3519879704,"remaining_time":1.614425272},
{"learn":[4.853838176],"iteration":179,"passed_time":0.3534186965,"remaining_time":1.610018506},
{"learn":[4.853462329],"iteration":180,"passed_time":0.3541214672,"remaining_time":1.602350727},
{"learn":[4.851573196],"iteration":181,"passed_time":0.35535653,"remaining_time":1.597151876},
{"learn":[4.848442087],"iteration":182,"passed_time":0.356449455,"remaining_time":1.591361774},
{"learn":[4.845547104],"iteration":183,"passed_time":0.3573834772,"remaining_time":1.584918029},
{"learn":[4.839868817],"iteration":184,"passed_time":0.3583808618,"remaining_time":1.578812986},
{"learn":[4.836336958],"iteration":185,"passed_time":0.3593462301,"remaining_time":1.572622749},
{"learn":[4.831124789],"iteration":186,"passed_time":0.3602934558,"remaining_time":1.566409517},
{"learn":[4.827407333],"iteration":187,"passed_time":0.361216789,"remaining_time":1.56014911},
{"learn":[4.824088918],"iteration":188,"passed_time":0.3621224608,"remaining_time":1.553869395},
{"learn":[4.820934539],"iteration":189,"passed_time":0.3630941296,"remaining_time":1.547927605},
{"learn":[4.816975227],"iteration":190,"passed_time":0.3640084067,"remaining_time":1.54179477},
{"learn":[4.812340486],"iteration":191,"passed_time":0.3648884028,"remaining_time":1.535572028},
{"learn":[4.806402747],"iteration":192,"passed_time":0.3658330539,"remaining_time":1.529674997},
{"learn":[4.801521788],"iteration":193,"passed_time":0.3667143122,"remaining_time":1.523565648},
{"learn":[4.797601172],"iteration":194,"passed_time":0.3676411717,"remaining_time":1.51769817},
{"learn":[4.792694629],"iteration":195,"passed_time":0.368507263,"remaining_time":1.511631834},
{"learn":[4.789794613],"iteration":196,"passed_time":0.3694319786,"remaining_time":1.505857253},
{"learn":[4.785367055],"iteration":197,"passed_time":0.3703838882,"remaining_time":1.50024181},
{"learn":[4.780376856],"iteration":198,"passed_time":0.3713016715,"remaining_time":1.494535874},
{"learn":[4.776691261],"iteration":199,"passed_time":0.3722079243,"remaining_time":1.488831697},
{"learn":[4.773470753],"iteration":200,"passed_time":0.3731140068,"remaining_time":1.483174584},
{"learn":[4.77207327],"iteration":201,"passed_time":0.3740122152,"remaining_time":1.477533405},
{"learn":[4.767347177],"iteration":202,"passed_time":0.37486338,"remaining_time":1.471754255},
{"learn":[4.763983068],"iteration":203,"passed_time":0.375765826,"remaining_time":1.466223517},
{"learn":[4.761588849],"iteration":204,"passed_time":0.3765911147,"remaining_time":1.460438713},
{"learn":[4.758558086],"iteration":205,"passed_time":0.3774376813,"remaining_time":1.454784073},
{"learn":[4.753678804],"iteration":206,"passed_time":0.3783267034,"remaining_time":1.44933853},
{"learn":[4.746510889],"iteration":207,"passed_time":0.3792032934,"remaining_time":1.443889463},
{"learn":[4.744840601],"iteration":208,"passed_time":0.3801070618,"remaining_time":1.438587014},
{"learn":[4.741702222],"iteration":209,"passed_time":0.3810283012,"remaining_time":1.433392181},
{"learn":[4.739352853],"iteration":210,"passed_time":0.3819453833,"remaining_time":1.42822231},
{"learn":[4.735539287],"iteration":211,"passed_time":0.3828874097,"remaining_time":1.423185278},
{"learn":[4.730726751],"iteration":212,"passed_time":0.3838392336,"remaining_time":1.418222896},
{"learn":[4.726416092],"iteration":213,"passed_time":0.384855943,"remaining_time":1.413536314},
{"learn":[4.721293082],"iteration":214,"passed_time":0.3857922092,"remaining_time":1.408590159},
{"learn":[4.718443695],"iteration":215,"passed_time":0.3867045428,"remaining_time":1.403594266},
{"learn":[4.711627962],"iteration":216,"passed_time":0.387642482,"remaining_time":1.398728403},
{"learn":[4.709790764],"iteration":217,"passed_time":0.3885492357,"remaining_time":1.393786708},
{"learn":[4.706913073],"iteration":218,"passed_time":0.389463653,"remaining_time":1.388909192},
{"learn":[4.703846389],"iteration":219,"passed_time":0.3903887994,"remaining_time":1.384105743},
{"learn":[4.701001135],"iteration":220,"passed_time":0.39129945,"remaining_time":1.379286297},
{"learn":[4.700380864],"iteration":221,"passed_time":0.3921853265,"remaining_time":1.374415243},
{"learn":[4.695837486],"iteration":222,"passed_time":0.3931184772,"remaining_time":1.369744649},
{"learn":[4.691242996],"iteration":223,"passed_time":0.3940273647,"remaining_time":1.36502337},
{"learn":[4.690284609],"iteration":224,"passed_time":0.3949590026,"remaining_time":1.360414342},
{"learn":[4.68827119],"iteration":225,"passed_time":0.3958906306,"remaining_time":1.355837823},
{"learn":[4.686922425],"iteration":226,"passed_time":0.3967960319,"remaining_time":1.351204109},
{"learn":[4.686085874],"iteration":227,"passed_time":0.3976823993,"remaining_time":1.34653865},
{"learn":[4.683230741],"iteration":228,"passed_time":0.3985694479,"remaining_time":1.34190849},
{"learn":[4.6773487],"iteration":229,"passed_time":0.399553459,"remaining_time":1.337635493},
{"learn":[4.671462906],"iteration":230,"passed_time":0.4004698699,"remaining_time":1.333165931},
{"learn":[4.664799601],"iteration":231,"passed_time":0.4014141704,"remaining_time":1.328819323},
{"learn":[4.660979386],"iteration":232,"passed_time":0.4023853788,"remaining_time":1.324590496},
{"learn":[4.656281279],"iteration":233,"passed_time":0.4032749319,"remaining_time":1.320122213},
{"learn":[4.651997094],"iteration":234,"passed_time":0.4042035344,"remaining_time":1.315811506},
{"learn":[4.650151977],"iteration":235,"passed_time":0.4051253249,"remaining_time":1.311507408},
{"learn":[4.648478046],"iteration":236,"passed_time":0.4060179434,"remaining_time":1.307137936},
{"learn":[4.646364602],"iteration":237,"passed_time":0.4068784748,"remaining_time":1.302694949},
{"learn":[4.642635873],"iteration":238,"passed_time":0.407867014,"remaining_time":1.29868953},
{"learn":[4.640860821],"iteration":239,"passed_time":0.4087584405,"remaining_time":1.294401728},
{"learn":[4.639446822],"iteration":240,"passed_time":0.4096674081,"remaining_time":1.290197356},
{"learn":[4.637120072],"iteration":241,"passed_time":0.4105129528,"remaining_time":1.285821563},
{"learn":[4.633769267],"iteration":242,"passed_time":0.4114607696,"remaining_time":1.281793426},
{"learn":[4.630491517],"iteration":243,"passed_time":0.4123174241,"remaining_time":1.277508085},
{"learn":[4.627813333],"iteration":244,"passed_time":0.4132333641,"remaining_time":1.273433428},
{"learn":[4.622496304],"iteration":245,"passed_time":0.4140902691,"remaining_time":1.269203508},
{"learn":[4.618979301],"iteration":246,"passed_time":0.4150088538,"remaining_time":1.265188935},
{"learn":[4.616563458],"iteration":247,"passed_time":0.4159114,"remaining_time":1.261150697},
{"learn":[4.614759385],"iteration":248,"passed_time":0.4168170217,"remaining_time":1.257146921},
{"learn":[4.61251363],"iteration":249,"passed_time":0.4177326412,"remaining_time":1.253197923},
{"learn":[4.608796693],"iteration":250,"passed_time":0.418655193,"remaining_time":1.249293783},
{"learn":[4.60847774],"iteration":251,"passed_time":0.419550326,"remaining_time":1.24533192},
{"learn":[4.605195659],"iteration":252,"passed_time":0.4204493559,"remaining_time":1.241405806},
{"learn":[4.60103766],"iteration":253,"passed_time":0.4213139646,"remaining_time":1.237402431},
{"learn":[4.599325598],"iteration":254,"passed_time":0.4221949223,"remaining_time":1.23347144},
{"learn":[4.597012808],"iteration":255,"passed_time":0.423100554,"remaining_time":1.229635985},
{"learn":[4.594161533],"iteration":256,"passed_time":0.4243449486,"remaining_time":1.226802711},
{"learn":[4.592197259],"iteration":257,"passed_time":0.4252593358,"remaining_time":1.223032664},
{"learn":[4.58952828],"iteration":258,"passed_time":0.4262020235,"remaining_time":1.219365635},
{"learn":[4.585816572],"iteration":259,"passed_time":0.4271380838,"remaining_time":1.2157007},
{"learn":[4.582934052],"iteration":260,"passed_time":0.42802939,"remaining_time":1.211929959},
{"learn":[4.582234842],"iteration":261,"passed_time":0.428907122,"remaining_time":1.208142962},
{"learn":[4.57571562],"iteration":262,"passed_time":0.4298808248,"remaining_time":1.204647026},
{"learn":[4.571197349],"iteration":263,"passed_time":0.4308435436,"remaining_time":1.201139576},
{"learn":[4.56723703],"iteration":264,"passed_time":0.4317374845,"remaining_time":1.19746057},
{"learn":[4.560335567],"iteration":265,"passed_time":0.4327551456,"remaining_time":1.194143898},
{"learn":[4.554709345],"iteration":266,"passed_time":0.4336736902,"remaining_time":1.190572341},
{"learn":[4.552806306],"iteration":267,"passed_time":0.4346154061,"remaining_time":1.18708387},
{"learn":[4.550766241],"iteration":268,"passed_time":0.4355253355,"remaining_time":1.183527956},
{"learn":[4.549216045],"iteration":269,"passed_time":0.4364499008,"remaining_time":1.180031213},
{"learn":[4.547687452],"iteration":270,"passed_time":0.437357506,"remaining_time":1.17650783},
{"learn":[4.545642435],"iteration":271,"passed_time":0.4382659676,"remaining_time":1.173005972},
{"learn":[4.543930359],"iteration":272,"passed_time":0.4391766983,"remaining_time":1.169529156},
{"learn":[4.541029943],"iteration":273,"passed_time":0.4400719916,"remaining_time":1.166030168},
{"learn":[4.537781449],"iteration":274,"passed_time":0.4409197403,"remaining_time":1.16242477},
{"learn":[4.53066128],"iteration":275,"passed_time":0.4418990227,"remaining_time":1.159184393},
{"learn":[4.526763956],"iteration":276,"passed_time":0.442820713,"remaining_time":1.15581002},
{"learn":[4.522036004],"iteration":277,"passed_time":0.4437273064,"remaining_time":1.152414083},
{"learn":[4.515307629],"iteration":278,"passed_time":0.4446083443,"remaining_time":1.148969951},
{"learn":[4.51109143],"iteration":279,"passed_time":0.4454966652,"remaining_time":1.145562853},
{"learn":[4.508233494],"iteration":280,"passed_time":0.4464224327,"remaining_time":1.142269499},
{"learn":[4.502555629],"iteration":281,"passed_time":0.4473468879,"remaining_time":1.138989594},
{"learn":[4.500081355],"iteration":282,"passed_time":0.4482125684,"remaining_time":1.135577426},
{"learn":[4.495281743],"iteration":283,"passed_time":0.4492827084,"remaining_time":1.132698659},
{"learn":[4.492138869],"iteration":284,"passed_time":0.4503308136,"remaining_time":1.129777304},
{"learn":[4.491708261],"iteration":285,"passed_time":0.4513302823,"remaining_time":1.126747628},
{"learn":[4.489398865],"iteration":286,"passed_time":0.452294463,"remaining_time":1.123644433},
{"learn":[4.485796373],"iteration":287,"passed_time":0.4533366077,"remaining_time":1.120748836},
{"learn":[4.479542205],"iteration":288,"passed_time":0.4543009939,"remaining_time":1.117674764},
{"learn":[4.475986993],"iteration":289,"passed_time":0.4551736669,"remaining_time":1.114390702},
{"learn":[4.468661855],"iteration":290,"passed_time":0.4561217842,"remaining_time":1.111307028},
{"learn":[4.463785664],"iteration":291,"passed_time":0.4570108164,"remaining_time":1.108094719},
{"learn":[4.460445831],"iteration":292,"passed_time":0.4580043645,"remaining_time":1.105150463},
{"learn":[4.45692492],"iteration":293,"passed_time":0.4588716079,"remaining_time":1.101916174},
{"learn":[4.454031688],"iteration":294,"passed_time":0.4598922943,"remaining_time":1.099064636},
{"learn":[4.451672391],"iteration":295,"passed_time":0.4608229105,"remaining_time":1.096011246},
{"learn":[4.45031553],"iteration":296,"passed_time":0.4617766578,"remaining_time":1.093026904},
{"learn":[4.446782666],"iteration":297,"passed_time":0.4627249454,"remaining_time":1.090043328},
{"learn":[4.444369689],"iteration":298,"passed_time":0.4636914153,"remaining_time":1.087115994},
{"learn":[4.44411683],"iteration":299,"passed_time":0.4645834528,"remaining_time":1.084028057},
{"learn":[4.440876943],"iteration":300,"passed_time":0.4654444851,"remaining_time":1.080882708},
{"learn":[4.439336453],"iteration":301,"passed_time":0.4663602894,"remaining_time":1.077879079},
{"learn":[4.436666901],"iteration":302,"passed_time":0.4672800763,"remaining_time":1.074898393},
{"learn":[4.433043336],"iteration":303,"passed_time":0.4681852872,"remaining_time":1.071897894},
{"learn":[4.431419305],"iteration":304,"passed_time":0.4691077689,"remaining_time":1.06895049},
{"learn":[4.428859646],"iteration":305,"passed_time":0.4700247007,"remaining_time":1.066003733},
{"learn":[4.424552441],"iteration":306,"passed_time":0.470953724,"remaining_time":1.063097494},
{"learn":[4.422706391],"iteration":307,"passed_time":0.4718165695,"remaining_time":1.060055409},
{"learn":[4.421427994],"iteration":308,"passed_time":0.4727045698,"remaining_time":1.057083682},
{"learn":[4.418733158],"iteration":309,"passed_time":0.4736490106,"remaining_time":1.054251024},
{"learn":[4.415656941],"iteration":310,"passed_time":0.4745628168,"remaining_time":1.051362639},
{"learn":[4.410747417],"iteration":311,"passed_time":0.4754593022,"remaining_time":1.048448718},
{"learn":[4.408126521],"iteration":312,"passed_time":0.4763638019,"remaining_time":1.045565278},
{"learn":[4.407843853],"iteration":313,"passed_time":0.4772797274,"remaining_time":1.042719404},
{"learn":[4.405219398],"iteration":314,"passed_time":0.4782180272,"remaining_time":1.03993444},
{"learn":[4.402708465],"iteration":315,"passed_time":0.4791026916,"remaining_time":1.037045067},
{"learn":[4.40104971],"iteration":316,"passed_time":0.4800282788,"remaining_time":1.034256512},
{"learn":[4.400830038],"iteration":317,"passed_time":0.4809453508,"remaining_time":1.031461413},
{"learn":[4.39784288],"iteration":318,"passed_time":0.4818618118,"remaining_time":1.028676783},
{"learn":[4.393741845],"iteration":319,"passed_time":0.4828367368,"remaining_time":1.026028066},
{"learn":[4.393425936],"iteration":320,"passed_time":0.4837100009,"remaining_time":1.023174737},
{"learn":[4.390505974],"iteration":321,"passed_time":0.4846770719,"remaining_time":1.020531226},
{"learn":[4.390305136],"iteration":322,"passed_time":0.4855699409,"remaining_time":1.01774257},
{"learn":[4.38568203],"iteration":323,"passed_time":0.4864605859,"remaining_time":1.014960975},
{"learn":[4.383057135],"iteration":324,"passed_time":0.4873816049,"remaining_time":1.012254103},
{"learn":[4.380662684],"iteration":325,"passed_time":0.4882918048,"remaining_time":1.009535817},
{"learn":[4.37805727],"iteration":326,"passed_time":0.4892248052,"remaining_time":1.006875516},
{"learn":[4.373708319],"iteration":327,"passed_time":0.4901732931,"remaining_time":1.004257479},
{"learn":[4.36887921],"iteration":328,"passed_time":0.4910843044,"remaining_time":1.001573156},
{"learn":[4.367895929],"iteration":329,"passed_time":0.4919801486,"remaining_time":0.9988687866},
{"learn":[4.362140573],"iteration":330,"passed_time":0.4929265228,"remaining_time":0.9962774736},
{"learn":[4.361931924],"iteration":331,"passed_time":0.4938061783,"remaining_time":0.9935618286},
{"learn":[4.359656377],"iteration":332,"passed_time":0.4947254442,"remaining_time":0.9909365504},
{"learn":[4.354281355],"iteration":333,"passed_time":0.4956557298,"remaining_time":0.9883434612},
{"learn":[4.348589447],"iteration":334,"passed_time":0.4965503118,"remaining_time":0.9856894249},
{"learn":[4.346355698],"iteration":335,"passed_time":0.4974600808,"remaining_time":0.9830758741},
{"learn":[4.343894047],"iteration":336,"passed_time":0.4983957961,"remaining_time":0.9805234801},
{"learn":[4.341561356],"iteration":337,"passed_time":0.4993825725,"remaining_time":0.9780806598},
{"learn":[4.338869061],"iteration":338,"passed_time":0.5003680162,"remaining_time":0.975643831},
{"learn":[4.333720063],"iteration":339,"passed_time":0.5013765711,"remaining_time":0.9732604027},
{"learn":[4.330892223],"iteration":340,"passed_time":0.502365511,"remaining_time":0.9708471313},
{"learn":[4.328311474],"iteration":341,"passed_time":0.5033005951,"remaining_time":0.9683385719},
{"learn":[4.324580133],"iteration":342,"passed_time":0.5042148221,"remaining_time":0.9657992365},
{"learn":[4.323354432],"iteration":343,"passed_time":0.5051345789,"remaining_time":0.9632798947},
{"learn":[4.323159553],"iteration":344,"passed_time":0.5060327273,"remaining_time":0.9607288011},
{"learn":[4.318639682],"iteration":345,"passed_time":0.5069957912,"remaining_time":0.9583099637},
{"learn":[4.312712208],"iteration":346,"passed_time":0.5078792534,"remaining_time":0.9557497189},
{"learn":[4.311461062],"iteration":347,"passed_time":0.5088209493,"remaining_time":0.9533082153},
{"learn":[4.311178356],"iteration":348,"passed_time":0.5097316099,"remaining_time":0.9508174156},
{"learn":[4.311102505],"iteration":349,"passed_time":0.5106595312,"remaining_time":0.9483677009},
{"learn":[4.310232308],"iteration":350,"passed_time":0.5115470707,"remaining_time":0.9458519912},
{"learn":[4.305128197],"iteration":351,"passed_time":0.5124324364,"remaining_time":0.9433415306},
{"learn":[4.304595496],"iteration":352,"passed_time":0.5134982628,"remaining_time":0.9411710369},
{"learn":[4.3004992],"iteration":353,"passed_time":0.5144677982,"remaining_time":0.9388310667},
{"learn":[4.297581524],"iteration":354,"passed_time":0.5153404913,"remaining_time":0.9363228644},
{"learn":[4.297355825],"iteration":355,"passed_time":0.5162376178,"remaining_time":0.9338680502},
{"learn":[4.295758715],"iteration":356,"passed_time":0.5171684944,"remaining_time":0.9314827504},
{"learn":[4.292500657],"iteration":357,"passed_time":0.5181257279,"remaining_time":0.9291528417},
{"learn":[4.290797586],"iteration":358,"passed_time":0.5190285947,"remaining_time":0.9267335075},
{"learn":[4.286410608],"iteration":359,"passed_time":0.5199488925,"remaining_time":0.9243535866},
{"learn":[4.280278245],"iteration":360,"passed_time":0.5208685792,"remaining_time":0.9219806706},
{"learn":[4.279941283],"iteration":361,"passed_time":0.5217415026,"remaining_time":0.9195333665},
{"learn":[4.274426275],"iteration":362,"passed_time":0.5226901509,"remaining_time":0.9172276201},
{"learn":[4.273567658],"iteration":363,"passed_time":0.5235952316,"remaining_time":0.9148532068},
{"learn":[4.269488271],"iteration":364,"passed_time":0.5245956419,"remaining_time":0.9126526921},
{"learn":[4.266838205],"iteration":365,"passed_time":0.5255214195,"remaining_time":0.9103294534},
{"learn":[4.263456509],"iteration":366,"passed_time":0.5265052704,"remaining_time":0.9081139949},
{"learn":[4.260360204],"iteration":367,"passed_time":0.5274467158,"remaining_time":0.9058324032},
{"learn":[4.255120549],"iteration":368,"passed_time":0.5283835931,"remaining_time":0.9035502635},
{"learn":[4.252582211],"iteration":369,"passed_time":0.5293090801,"remaining_time":0.9012560012},
{"learn":[4.247857931],"iteration":370,"passed_time":0.530227194,"remaining_time":0.8989566173},
{"learn":[4.245288911],"iteration":371,"passed_time":0.531131303,"remaining_time":0.8966410168},
{"learn":[4.24048515],"iteration":372,"passed_time":0.5319988669,"remaining_time":0.8942715537},
{"learn":[4.2378365],"iteration":373,"passed_time":0.5328538384,"remaining_time":0.8918890451},
{"learn":[4.236751063],"iteration":374,"passed_time":0.5337147706,"remaining_time":0.8895246176},
{"learn":[4.233240093],"iteration":375,"passed_time":0.5346154835,"remaining_time":0.8872342066},
{"learn":[4.230358421],"iteration":376,"passed_time":0.5355917709,"remaining_time":0.8850760564},
{"learn":[4.225853583],"iteration":377,"passed_time":0.5364735602,"remaining_time":0.8827686625},
{"learn":[4.224702126],"iteration":378,"passed_time":0.5373115314,"remaining_time":0.8803969948},
{"learn":[4.224361982],"iteration":379,"passed_time":0.5382034587,"remaining_time":0.8781214327},
{"learn":[4.223787954],"iteration":380,"passed_time":0.5392132261,"remaining_time":0.8760445852},
{"learn":[4.22144054],"iteration":381,"passed_time":0.5400896458,"remaining_time":0.8737575945},
{"learn":[4.217739335],"iteration":382,"passed_time":0.541025331,"remaining_time":0.8715734444},
{"learn":[4.215611665],"iteration":383,"passed_time":0.5420078512,"remaining_time":0.869470928},
{"learn":[4.210236863],"iteration":384,"passed_time":0.5430288682,"remaining_time":0.8674357246},
{"learn":[4.208454294],"iteration":385,"passed_time":0.5439730385,"remaining_time":0.8652835379},
{"learn":[4.207446501],"iteration":386,"passed_time":0.5448908118,"remaining_time":0.863095782},
{"learn":[4.204985442],"iteration":387,"passed_time":0.5457877881,"remaining_time":0.8608817688},
{"learn":[4.202796622],"iteration":388,"passed_time":0.5466815186,"remaining_time":0.8586694289},
{"learn":[4.199774004],"iteration":389,"passed_time":0.5476117841,"remaining_time":0.8565209956},
{"learn":[4.199458358],"iteration":390,"passed_time":0.5485192691,"remaining_time":0.8543433117},
{"learn":[4.19751254],"iteration":391,"passed_time":0.5495047256,"remaining_time":0.8522930437},
{"learn":[4.195201346],"iteration":392,"passed_time":0.5504885965,"remaining_time":0.8502457457},
{"learn":[4.190593508],"iteration":393,"passed_time":0.5513863341,"remaining_time":0.8480713667},
{"learn":[4.187212054],"iteration":394,"passed_time":0.5522533371,"remaining_time":0.845856377},
{"learn":[4.184984466],"iteration":395,"passed_time":0.553129877,"remaining_time":0.8436627417},
{"learn":[4.182832144],"iteration":396,"passed_time":0.5540400167,"remaining_time":0.841526776},
{"learn":[4.179752812],"iteration":397,"passed_time":0.5549585914,"remaining_time":0.8394097287},
{"learn":[4.17878934],"iteration":398,"passed_time":0.555868651,"remaining_time":0.8372858627},
{"learn":[4.174548229],"iteration":399,"passed_time":0.5567474048,"remaining_time":0.8351211072},
{"learn":[4.168872556],"iteration":400,"passed_time":0.5576182245,"remaining_time":0.832950914},
{"learn":[4.163926494],"iteration":401,"passed_time":0.5585491312,"remaining_time":0.8308765683},
{"learn":[4.159485076],"iteration":402,"passed_time":0.559409883,"remaining_time":0.8287039706},
{"learn":[4.155926102],"iteration":403,"passed_time":0.5602890777,"remaining_time":0.826565075},
{"learn":[4.153540115],"iteration":404,"passed_time":0.5612186319,"remaining_time":0.8245063852},
{"learn":[4.150983044],"iteration":405,"passed_time":0.5621502699,"remaining_time":0.8224563062},
{"learn":[4.146539132],"iteration":406,"passed_time":0.5630873375,"remaining_time":0.8204196343},
{"learn":[4.144869174],"iteration":407,"passed_time":0.5639993005,"remaining_time":0.8183519262},
{"learn":[4.142825962],"iteration":408,"passed_time":0.5648991519,"remaining_time":0.8162723686},
{"learn":[4.142467378],"iteration":409,"passed_time":0.5657850584,"remaining_time":0.8141784987},
{"learn":[4.141800768],"iteration":410,"passed_time":0.5666868032,"remaining_time":0.8121132046},
{"learn":[4.140107084],"iteration":411,"passed_time":0.5676041257,"remaining_time":0.810075791},
{"learn":[4.136243196],"iteration":412,"passed_time":0.5684809661,"remaining_time":0.8079862642},
{"learn":[4.133618439],"iteration":413,"passed_time":0.5693454145,"remaining_time":0.8058850554},
{"learn":[4.131053025],"iteration":414,"passed_time":0.5702832736,"remaining_time":0.8038932893},
{"learn":[4.128379975],"iteration":415,"passed_time":0.5711458987,"remaining_time":0.8018009732},
{"learn":[4.127068571],"iteration":416,"passed_time":0.5720515304,"remaining_time":0.7997746816},
{"learn":[4.125969877],"iteration":417,"passed_time":0.5729582039,"remaining_time":0.7977552026},
{"learn":[4.123893633],"iteration":418,"passed_time":0.5738733926,"remaining_time":0.7957528428},
{"learn":[4.119643722],"iteration":419,"passed_time":0.574896844,"remaining_time":0.7939051655},
{"learn":[4.11465686],"iteration":420,"passed_time":0.5757795449,"remaining_time":0.7918678301},
{"learn":[4.111565986],"iteration":421,"passed_time":0.57668712,"remaining_time":0.7898700364},
{"learn":[4.106322452],"iteration":422,"passed_time":0.5775787768,"remaining_time":0.7878556838},
{"learn":[4.104222175],"iteration":423,"passed_time":0.5784536337,"remaining_time":0.7858238043},
{"learn":[4.103008002],"iteration":424,"passed_time":0.5793353228,"remaining_time":0.7838066132},
{"learn":[4.099176337],"iteration":425,"passed_time":0.5801955236,"remaining_time":0.7817657995},
{"learn":[4.096525716],"iteration":426,"passed_time":0.5811280532,"remaining_time":0.7798275749},
{"learn":[4.094967724],"iteration":427,"passed_time":0.5820460369,"remaining_time":0.77787461},
{"learn":[4.094683584],"iteration":428,"passed_time":0.5829313123,"remaining_time":0.7758829355},
{"learn":[4.091096563],"iteration":429,"passed_time":0.5838381161,"remaining_time":0.7739249446},
{"learn":[4.089178677],"iteration":430,"passed_time":0.5848343134,"remaining_time":0.7720898477},
{"learn":[4.085335077],"iteration":431,"passed_time":0.5857331931,"remaining_time":0.7701306798},
{"learn":[4.084852122],"iteration":432,"passed_time":0.5866223655,"remaining_time":0.768163698},
{"learn":[4.080322952],"iteration":433,"passed_time":0.5875096245,"remaining_time":0.7661991877},
{"learn":[4.077449519],"iteration":434,"passed_time":0.5884583729,"remaining_time":0.7643194958},
{"learn":[4.076568374],"iteration":435,"passed_time":0.5893864044,"remaining_time":0.7624172755},
{"learn":[4.076071793],"iteration":436,"passed_time":0.5902966143,"remaining_time":0.7604965534},
{"learn":[4.075027644],"iteration":437,"passed_time":0.5912498206,"remaining_time":0.7586356146},
{"learn":[4.07020837],"iteration":438,"passed_time":0.5923222547,"remaining_time":0.7569311728},
{"learn":[4.06833694],"iteration":439,"passed_time":0.5932527105,"remaining_time":0.7550489043},
{"learn":[4.063936568],"iteration":440,"passed_time":0.5941936951,"remaining_time":0.7531842984},
{"learn":[4.061734926],"iteration":441,"passed_time":0.5952212438,"remaining_time":0.7514331539},
{"learn":[4.060815619],"iteration":442,"passed_time":0.5961759677,"remaining_time":0.749593711},
{"learn":[4.056407489],"iteration":443,"passed_time":0.5970837031,"remaining_time":0.747699412},
{"learn":[4.05238936],"iteration":444,"passed_time":0.5979598623,"remaining_time":0.7457701654},
{"learn":[4.049685254],"iteration":445,"passed_time":0.5988914101,"remaining_time":0.7439144422},
{"learn":[4.045162016],"iteration":446,"passed_time":0.5998868817,"remaining_time":0.7421419364},
{"learn":[4.042955482],"iteration":447,"passed_time":0.6007778473,"remaining_time":0.7402441332},
{"learn":[4.041467663],"iteration":448,"passed_time":0.6016961715,"remaining_time":0.7383843887},
{"learn":[4.038920476],"iteration":449,"passed_time":0.6026808439,"remaining_time":0.7366099203},
{"learn":[4.036694383],"iteration":450,"passed_time":0.6036495679,"remaining_time":0.7348195405},
{"learn":[4.034999007],"iteration":451,"passed_time":0.6045141565,"remaining_time":0.7329065437},
{"learn":[4.031928018],"iteration":452,"passed_time":0.6054967051,"remaining_time":0.731140613},
{"learn":[4.028718143],"iteration":453,"passed_time":0.6065845662,"remaining_time":0.7295047867},
{"learn":[4.027401978],"iteration":454,"passed_time":0.6074839668,"remaining_time":0.7276456306},
{"learn":[4.025930598],"iteration":455,"passed_time":0.6083929044,"remaining_time":0.7258020614},
{"learn":[4.021074523],"iteration":456,"passed_time":0.6092662386,"remaining_time":0.7239202791},
{"learn":[4.020268486],"iteration":457,"passed_time":0.6101899873,"remaining_time":0.7221025614},
{"learn":[4.017986361],"iteration":458,"passed_time":0.6111516988,"remaining_time":0.7203334838},
{"learn":[4.014814804],"iteration":459,"passed_time":0.6121110962,"remaining_time":0.7185651999},
{"learn":[4.009704796],"iteration":460,"passed_time":0.6131045942,"remaining_time":0.7168402957},
{"learn":[4.008440457],"iteration":461,"passed_time":0.6140049217,"remaining_time":0.7150100603},
{"learn":[4.004854849],"iteration":462,"passed_time":0.6149515964,"remaining_time":0.7132375967},
{"learn":[4.000898028],"iteration":463,"passed_time":0.615958348,"remaining_time":0.7115380917},
{"learn":[3.996617985],"iteration":464,"passed_time":0.6168947244,"remaining_time":0.7097605969},
{"learn":[3.995443319],"iteration":465,"passed_time":0.617742954,"remaining_time":0.7078857026},
{"learn":[3.990771995],"iteration":466,"passed_time":0.6186676295,"remaining_time":0.7061024551},
{"learn":[3.989249359],"iteration":467,"passed_time":0.6195785606,"remaining_time":0.7043072527},
{"learn":[3.986599538],"iteration":468,"passed_time":0.6204424781,"remaining_time":0.7024625925},
{"learn":[3.985628919],"iteration":469,"passed_time":0.6215213781,"remaining_time":0.7008645328},
{"learn":[3.985086112],"iteration":470,"passed_time":0.6223780226,"remaining_time":0.699019053},
{"learn":[3.98466839],"iteration":471,"passed_time":0.6233573956,"remaining_time":0.6973150527},
{"learn":[3.984233894],"iteration":472,"passed_time":0.6242700698,"remaining_time":0.6955398029},
{"learn":[3.981855845],"iteration":473,"passed_time":0.6251954065,"remaining_time":0.6937822444},
{"learn":[3.978684264],"iteration":474,"passed_time":0.6260678692,"remaining_time":0.6919697501},
{"learn":[3.974361269],"iteration":475,"passed_time":0.6269519525,"remaining_time":0.6901739981},
{"learn":[3.972074049],"iteration":476,"passed_time":0.6278636951,"remaining_time":0.6884123952},
{"learn":[3.97191982],"iteration":477,"passed_time":0.6287860866,"remaining_time":0.6866659774},
{"learn":[3.969616848],"iteration":478,"passed_time":0.6296652311,"remaining_time":0.6848759612},
{"learn":[3.968533527],"iteration":479,"passed_time":0.6305971396,"remaining_time":0.6831469012},
{"learn":[3.967568753],"iteration":480,"passed_time":0.6314662563,"remaining_time":0.6813534033},
{"learn":[3.966232553],"iteration":481,"passed_time":0.6323375368,"remaining_time":0.6795660665},
{"learn":[3.961522393],"iteration":482,"passed_time":0.6332072746,"remaining_time":0.6777808716},
{"learn":[3.955829553],"iteration":483,"passed_time":0.6341755378,"remaining_time":0.676104499},
{"learn":[3.954248095],"iteration":484,"passed_time":0.6351227735,"remaining_time":0.6744087183},
{"learn":[3.951922606],"iteration":485,"passed_time":0.6360887073,"remaining_time":0.6727357933},
{"learn":[3.94978202],"iteration":486,"passed_time":0.6371107161,"remaining_time":0.6711248406},
{"learn":[3.949518999],"iteration":487,"passed_time":0.6380090148,"remaining_time":0.6693865073},
{"learn":[3.945431216],"iteration":488,"passed_time":0.6389864843,"remaining_time":0.6677343425},
{"learn":[3.943249086],"iteration":489,"passed_time":0.6399208271,"remaining_time":0.6660400445},
{"learn":[3.941981548],"iteration":490,"passed_time":0.640834453,"remaining_time":0.6643273657},
{"learn":[3.936600517],"iteration":491,"passed_time":0.6417903341,"remaining_time":0.6626615645},
{"learn":[3.934476885],"iteration":492,"passed_time":0.6427034287,"remaining_time":0.6609546417},
{"learn":[3.93045798],"iteration":493,"passed_time":0.6436402359,"remaining_time":0.6592752213},
{"learn":[3.925977375],"iteration":494,"passed_time":0.6446185269,"remaining_time":0.6576411234},
{"learn":[3.92457993],"iteration":495,"passed_time":0.6454914804,"remaining_time":0.6559026333},
{"learn":[3.919849146],"iteration":496,"passed_time":0.6464488745,"remaining_time":0.6542530863},
{"learn":[3.919681964],"iteration":497,"passed_time":0.6472811757,"remaining_time":0.6524802213},
{"learn":[3.917633027],"iteration":498,"passed_time":0.6482039279,"remaining_time":0.6508019396},
{"learn":[3.916616419],"iteration":499,"passed_time":0.6491010344,"remaining_time":0.6491010344},
{"learn":[3.912896166],"iteration":500,"passed_time":0.6500789298,"remaining_time":0.6474838044},
{"learn":[3.912769674],"iteration":501,"passed_time":0.6509352838,"remaining_time":0.6457485485},
{"learn":[3.909373788],"iteration":502,"passed_time":0.6518308776,"remaining_time":0.644055559},
{"learn":[3.906706036],"iteration":503,"passed_time":0.6527259205,"remaining_time":0.6423651916},
{"learn":[3.903895664],"iteration":504,"passed_time":0.6536489131,"remaining_time":0.6407053702},
{"learn":[3.902982967],"iteration":505,"passed_time":0.6546171862,"remaining_time":0.639092668},
{"learn":[3.900905528],"iteration":506,"passed_time":0.655562208,"remaining_time":0.6374598985},
{"learn":[3.897463465],"iteration":507,"passed_time":0.6565477567,"remaining_time":0.6358690872},
{"learn":[3.895918033],"iteration":508,"passed_time":0.6574549111,"remaining_time":0.6342050322},
{"learn":[3.893921936],"iteration":509,"passed_time":0.6583775431,"remaining_time":0.6325588159},
{"learn":[3.890237934],"iteration":510,"passed_time":0.6593655113,"remaining_time":0.630977955},
{"learn":[3.887311613],"iteration":511,"passed_time":0.6602443353,"remaining_time":0.629295382},
{"learn":[3.884869735],"iteration":512,"passed_time":0.6612016389,"remaining_time":0.6276904447},
{"learn":[3.882101231],"iteration":513,"passed_time":0.6620689223,"remaining_time":0.626002911},
{"learn":[3.88060368],"iteration":514,"passed_time":0.6630152965,"remaining_time":0.6243930462},
{"learn":[3.877726076],"iteration":515,"passed_time":0.6639313267,"remaining_time":0.622757291},
{"learn":[3.874938145],"iteration":516,"passed_time":0.6649582194,"remaining_time":0.6212278916},
{"learn":[3.874340833],"iteration":517,"passed_time":0.6658920913,"remaining_time":0.6196138765},
{"learn":[3.873105224],"iteration":518,"passed_time":0.6667380869,"remaining_time":0.61792104},
{"learn":[3.869800236],"iteration":519,"passed_time":0.6676656376,"remaining_time":0.6163067424},
{"learn":[3.867932518],"iteration":520,"passed_time":0.6685336122,"remaining_time":0.6146403076},
{"learn":[3.866666962],"iteration":521,"passed_time":0.669394334,"remaining_time":0.6129702905},
{"learn":[3.865527652],"iteration":522,"passed_time":0.6702993145,"remaining_time":0.6113437343},
{"learn":[3.861900081],"iteration":523,"passed_time":0.6712244008,"remaining_time":0.6097381962},
{"learn":[3.858502887],"iteration":524,"passed_time":0.6721264261,"remaining_time":0.6081143855},
{"learn":[3.858335097],"iteration":525,"passed_time":0.6730033066,"remaining_time":0.6064706603},
{"learn":[3.855719306],"iteration":526,"passed_time":0.6738931802,"remaining_time":0.6048415071},
{"learn":[3.855137428],"iteration":527,"passed_time":0.6748029593,"remaining_time":0.6032329485},
{"learn":[3.851985706],"iteration":528,"passed_time":0.6758224084,"remaining_time":0.6017246774},
{"learn":[3.851051809],"iteration":529,"passed_time":0.6767044481,"remaining_time":0.6000963973},
{"learn":[3.850679146],"iteration":530,"passed_time":0.6775914867,"remaining_time":0.5984753432},
{"learn":[3.848179484],"iteration":531,"passed_time":0.6785675938,"remaining_time":0.596935402},
{"learn":[3.844551071],"iteration":532,"passed_time":0.6795928684,"remaining_time":0.5954406558},
{"learn":[3.841604794],"iteration":533,"passed_time":0.680643248,"remaining_time":0.593969576},
{"learn":[3.83969656],"iteration":534,"passed_time":0.6815901732,"remaining_time":0.5924101505},
{"learn":[3.836811463],"iteration":535,"passed_time":0.6825203285,"remaining_time":0.5908384933},
{"learn":[3.834182551],"iteration":536,"passed_time":0.6835219666,"remaining_time":0.5893308576},
{"learn":[3.828012842],"iteration":537,"passed_time":0.6845085623,"remaining_time":0.5878121855},
{"learn":[3.826636176],"iteration":538,"passed_time":0.6854711754,"remaining_time":0.5862749756},
{"learn":[3.826189798],"iteration":539,"passed_time":0.6863645753,"remaining_time":0.5846809345},
{"learn":[3.824104738],"iteration":540,"passed_time":0.6873139248,"remaining_time":0.5831369528},
{"learn":[3.82300218],"iteration":541,"passed_time":0.6882385202,"remaining_time":0.5815742477},
{"learn":[3.817146402],"iteration":542,"passed_time":0.6891496617,"remaining_time":0.5800025698},
{"learn":[3.814638044],"iteration":543,"passed_time":0.6901640017,"remaining_time":0.578519825},
{"learn":[3.812979573],"iteration":544,"passed_time":0.6910897492,"remaining_time":0.5769648365},
{"learn":[3.811938825],"iteration":545,"passed_time":0.6919577439,"remaining_time":0.5753641314},
{"learn":[3.811479418],"iteration":546,"passed_time":0.6928704381,"remaining_time":0.5738031234},
{"learn":[3.80742981],"iteration":547,"passed_time":0.6938743247,"remaining_time":0.5723196985},
{"learn":[3.805097043],"iteration":548,"passed_time":0.6947808379,"remaining_time":0.570758029},
{"learn":[3.801577232],"iteration":549,"passed_time":0.695698481,"remaining_time":0.5692078481},
{"learn":[3.799762083],"iteration":550,"passed_time":0.6965965392,"remaining_time":0.5676440038},
{"learn":[3.796393455],"iteration":551,"passed_time":0.69746796,"remaining_time":0.566060953},
{"learn":[3.793486459],"iteration":552,"passed_time":0.6983787909,"remaining_time":0.5645123319},
{"learn":[3.792006091],"iteration":553,"passed_time":0.6992798244,"remaining_time":0.5629581258},
{"learn":[3.78932128],"iteration":554,"passed_time":0.70017097,"remaining_time":0.5613983453},
{"learn":[3.787581812],"iteration":555,"passed_time":0.7010446849,"remaining_time":0.5598270505},
{"learn":[3.785308865],"iteration":556,"passed_time":0.7019871822,"remaining_time":0.5583129654},
{"learn":[3.78465475],"iteration":557,"passed_time":0.7028895581,"remaining_time":0.5567691481},
{"learn":[3.780498869],"iteration":558,"passed_time":0.7038697929,"remaining_time":0.5552890495},
{"learn":[3.778734909],"iteration":559,"passed_time":0.7047993371,"remaining_time":0.5537709077},
{"learn":[3.778652349],"iteration":560,"passed_time":0.7057114002,"remaining_time":0.5522411848},
{"learn":[3.777928006],"iteration":561,"passed_time":0.7065789141,"remaining_time":0.5506789402},
{"learn":[3.776131406],"iteration":562,"passed_time":0.7074777637,"remaining_time":0.5491434862},
{"learn":[3.772925617],"iteration":563,"passed_time":0.7086022048,"remaining_time":0.5477846831},
{"learn":[3.7727745],"iteration":564,"passed_time":0.7095016855,"remaining_time":0.5462535101},
{"learn":[3.771763073],"iteration":565,"passed_time":0.7104208012,"remaining_time":0.5447396249},
{"learn":[3.768738162],"iteration":566,"passed_time":0.7113549236,"remaining_time":0.5432392979},
{"learn":[3.767220794],"iteration":567,"passed_time":0.7122443364,"remaining_time":0.5417069601},
{"learn":[3.766691102],"iteration":568,"passed_time":0.7131558686,"remaining_time":0.5401936368},
{"learn":[3.766259335],"iteration":569,"passed_time":0.7139999507,"remaining_time":0.5386315418},
{"learn":[3.76116362],"iteration":570,"passed_time":0.7150308598,"remaining_time":0.5372123273},
{"learn":[3.758633056],"iteration":571,"passed_time":0.7159212644,"remaining_time":0.5356893377},
{"learn":[3.754603809],"iteration":572,"passed_time":0.7168831262,"remaining_time":0.5342218061},
{"learn":[3.754070549],"iteration":573,"passed_time":0.7177373063,"remaining_time":0.5326761193},
{"learn":[3.750534319],"iteration":574,"passed_time":0.7187515913,"remaining_time":0.5312511762},
{"learn":[3.746491516],"iteration":575,"passed_time":0.7196311767,"remaining_time":0.5297285051},
{"learn":[3.744210544],"iteration":576,"passed_time":0.7205390624,"remaining_time":0.52822881},
{"learn":[3.742929991],"iteration":577,"passed_time":0.721406426,"remaining_time":0.5267015774},
{"learn":[3.740402992],"iteration":578,"passed_time":0.7224112739,"remaining_time":0.5252765912},
{"learn":[3.739644243],"iteration":579,"passed_time":0.7233341262,"remaining_time":0.5237936776},
{"learn":[3.737529404],"iteration":580,"passed_time":0.7242896166,"remaining_time":0.5223362295},
{"learn":[3.737196923],"iteration":581,"passed_time":0.7251986944,"remaining_time":0.5208471723},
{"learn":[3.733954464],"iteration":582,"passed_time":0.7261435359,"remaining_time":0.5193856852},
{"learn":[3.731608623],"iteration":583,"passed_time":0.7269841519,"remaining_time":0.5178517246},
{"learn":[3.729843952],"iteration":584,"passed_time":0.7279366469,"remaining_time":0.5163995017},
{"learn":[3.727223798],"iteration":585,"passed_time":0.7288147797,"remaining_time":0.5148964485},
{"learn":[3.725351667],"iteration":586,"passed_time":0.7297830829,"remaining_time":0.5134589663},
{"learn":[3.725026912],"iteration":587,"passed_time":0.7306858094,"remaining_time":0.5119771318},
{"learn":[3.721974565],"iteration":588,"passed_time":0.7315680094,"remaining_time":0.5104829404},
{"learn":[3.720269493],"iteration":589,"passed_time":0.7324388592,"remaining_time":0.508982936},
{"learn":[3.718907466],"iteration":590,"passed_time":0.7333592371,"remaining_time":0.5075193367},
{"learn":[3.715602912],"iteration":591,"passed_time":0.7343467645,"remaining_time":0.5061038512},
{"learn":[3.714463059],"iteration":592,"passed_time":0.735234274,"remaining_time":0.5046211627},
{"learn":[3.710802077],"iteration":593,"passed_time":0.7361385436,"remaining_time":0.5031519338},
{"learn":[3.708032435],"iteration":594,"passed_time":0.7371472988,"remaining_time":0.5017557244},
{"learn":[3.703788939],"iteration":595,"passed_time":0.7380994432,"remaining_time":0.5003224414},
{"learn":[3.702500944],"iteration":596,"passed_time":0.7390991323,"remaining_time":0.4989228649},
{"learn":[3.698196925],"iteration":597,"passed_time":0.7400892796,"remaining_time":0.4975182114},
{"learn":[3.69658891],"iteration":598,"passed_time":0.7409944304,"remaining_time":0.4960580411},
{"learn":[3.696124066],"iteration":599,"passed_time":0.7419279718,"remaining_time":0.4946186478},
{"learn":[3.693537052],"iteration":600,"passed_time":0.7428262403,"remaining_time":0.4931575206},
{"learn":[3.691343275],"iteration":601,"passed_time":0.7438214736,"remaining_time":0.4917623696},
{"learn":[3.690973831],"iteration":602,"passed_time":0.7447723858,"remaining_time":0.4903393651},
{"learn":[3.686151073],"iteration":603,"passed_time":0.7457436343,"remaining_time":0.4889312569},
{"learn":[3.683921982],"iteration":604,"passed_time":0.7467222559,"remaining_time":0.4875294067},
{"learn":[3.679975271],"iteration":605,"passed_time":0.7475814349,"remaining_time":0.4860512959},
{"learn":[3.674047638],"iteration":606,"passed_time":0.7485050986,"remaining_time":0.4846169749},
{"learn":[3.673151794],"iteration":607,"passed_time":0.7494098888,"remaining_time":0.4831721652},
{"learn":[3.670953108],"iteration":608,"passed_time":0.7502976788,"remaining_time":0.4817182141},
{"learn":[3.6703947],"iteration":609,"passed_time":0.75131547,"remaining_time":0.4803492349},
{"learn":[3.668433805],"iteration":610,"passed_time":0.7523019456,"remaining_time":0.4789614678},
{"learn":[3.668304956],"iteration":611,"passed_time":0.7532109833,"remaining_time":0.4775259175},
{"learn":[3.667880012],"iteration":612,"passed_time":0.7541257212,"remaining_time":0.4760956837},
{"learn":[3.667282264],"iteration":613,"passed_time":0.7550069495,"remaining_time":0.4746460627},
{"learn":[3.664611483],"iteration":614,"passed_time":0.7559305832,"remaining_time":0.4732248366},
{"learn":[3.662543394],"iteration":615,"passed_time":0.7569062395,"remaining_time":0.4718376558},
{"learn":[3.659041959],"iteration":616,"passed_time":0.7579305151,"remaining_time":0.4704819891},
{"learn":[3.656868545],"iteration":617,"passed_time":0.7588599992,"remaining_time":0.4690688021},
{"learn":[3.654785614],"iteration":618,"passed_time":0.7597239968,"remaining_time":0.4676168704},
{"learn":[3.654566096],"iteration":619,"passed_time":0.7605948967,"remaining_time":0.4661710657},
{"learn":[3.651007045],"iteration":620,"passed_time":0.7615179991,"remaining_time":0.4647589721},
{"learn":[3.648921786],"iteration":621,"passed_time":0.7625332158,"remaining_time":0.4634044302},
{"learn":[3.647655706],"iteration":622,"passed_time":0.7634942762,"remaining_time":0.4620182056},
{"learn":[3.647241144],"iteration":623,"passed_time":0.7644181403,"remaining_time":0.4606109307},
{"learn":[3.644195689],"iteration":624,"passed_time":0.7653757901,"remaining_time":0.459225474},
{"learn":[3.642632246],"iteration":625,"passed_time":0.7662476516,"remaining_time":0.4577901305},
{"learn":[3.642523322],"iteration":626,"passed_time":0.7669572745,"remaining_time":0.4562600692},
{"learn":[3.641494659],"iteration":627,"passed_time":0.7678664024,"remaining_time":0.4548507989},
{"learn":[3.63976496],"iteration":628,"passed_time":0.7687372722,"remaining_time":0.4534205533},
{"learn":[3.637945652],"iteration":629,"passed_time":0.7696187309,"remaining_time":0.4519983023},
{"learn":[3.636233667],"iteration":630,"passed_time":0.7705370952,"remaining_time":0.4505993473},
{"learn":[3.635304404],"iteration":631,"passed_time":0.7714416951,"remaining_time":0.4491938984},
{"learn":[3.632234951],"iteration":632,"passed_time":0.7724280003,"remaining_time":0.447837403},
{"learn":[3.631630987],"iteration":633,"passed_time":0.7733565729,"remaining_time":0.4464487471},
{"learn":[3.630301009],"iteration":634,"passed_time":0.7742332029,"remaining_time":0.4450316836},
{"learn":[3.629077964],"iteration":635,"passed_time":0.7751539615,"remaining_time":0.4436415755},
{"learn":[3.628004522],"iteration":636,"passed_time":0.7760760425,"remaining_time":0.4422536945},
{"learn":[3.625062876],"iteration":637,"passed_time":0.7769374354,"remaining_time":0.4408328395},
{"learn":[3.624917986],"iteration":638,"passed_time":0.7777850539,"remaining_time":0.4394059538},
{"learn":[3.622887087],"iteration":639,"passed_time":0.7787422573,"remaining_time":0.4380425198},
{"learn":[3.621220865],"iteration":640,"passed_time":0.7796834223,"remaining_time":0.4366713707},
{"learn":[3.621143844],"iteration":641,"passed_time":0.7805436932,"remaining_time":0.435256452},
{"learn":[3.620822821],"iteration":642,"passed_time":0.7814551052,"remaining_time":0.4338716525},
{"learn":[3.619202826],"iteration":643,"passed_time":0.7823446182,"remaining_time":0.4324762175},
{"learn":[3.618204882],"iteration":644,"passed_time":0.7832380381,"remaining_time":0.4310845016},
{"learn":[3.614259666],"iteration":645,"passed_time":0.7841665205,"remaining_time":0.4297135422},
{"learn":[3.613415661],"iteration":646,"passed_time":0.7850102119,"remaining_time":0.4282976891},
{"learn":[3.611096773],"iteration":647,"passed_time":0.7858664257,"remaining_time":0.4268904041},
{"learn":[3.610820695],"iteration":648,"passed_time":0.7867864029,"remaining_time":0.4255193026},
{"learn":[3.609290065],"iteration":649,"passed_time":0.787682157,"remaining_time":0.4241365461},
{"learn":[3.60897947],"iteration":650,"passed_time":0.7885735433,"remaining_time":0.4227529441},
{"learn":[3.606570702],"iteration":651,"passed_time":0.7895069945,"remaining_time":0.4213933038},
{"learn":[3.606292637],"iteration":652,"passed_time":0.7903575081,"remaining_time":0.4199908964},
{"learn":[3.602753838],"iteration":653,"passed_time":0.7913763413,"remaining_time":0.4186792264},
{"learn":[3.599755869],"iteration":654,"passed_time":0.7922552955,"remaining_time":0.417294774},
{"learn":[3.599509575],"iteration":655,"passed_time":0.7931846995,"remaining_time":0.415938318},
{"learn":[3.595337722],"iteration":656,"passed_time":0.7941698126,"remaining_time":0.4146122461},
{"learn":[3.595168561],"iteration":657,"passed_time":0.7950305444,"remaining_time":0.4132225626},
{"learn":[3.59290559],"iteration":658,"passed_time":0.7959046099,"remaining_time":0.4118413839},
{"learn":[3.592015928],"iteration":659,"passed_time":0.7967583592,"remaining_time":0.410451276},
{"learn":[3.590680403],"iteration":660,"passed_time":0.7976703222,"remaining_time":0.4090926463},
{"learn":[3.590361532],"iteration":661,"passed_time":0.7986141118,"remaining_time":0.407751616},
{"learn":[3.589069739],"iteration":662,"passed_time":0.7994848313,"remaining_time":0.4063746428},
{"learn":[3.585010186],"iteration":663,"passed_time":0.800332039,"remaining_time":0.4049872969},
{"learn":[3.582997552],"iteration":664,"passed_time":0.8013144273,"remaining_time":0.4036696739},
{"learn":[3.582119256],"iteration":665,"passed_time":0.8022331022,"remaining_time":0.4023211053},
{"learn":[3.579019356],"iteration":666,"passed_time":0.8031128879,"remaining_time":0.4009544103},
{"learn":[3.57719559],"iteration":667,"passed_time":0.8040379742,"remaining_time":0.3996116878},
{"learn":[3.574050046],"iteration":668,"passed_time":0.8049921222,"remaining_time":0.3982845926},
{"learn":[3.572204518],"iteration":669,"passed_time":0.8058600669,"remaining_time":0.3969161523},
{"learn":[3.569508025],"iteration":670,"passed_time":0.8068134134,"remaining_time":0.3955910775},
{"learn":[3.566268704],"iteration":671,"passed_time":0.807708837,"remaining_time":0.3942388371},
{"learn":[3.562564052],"iteration":672,"passed_time":0.8088398902,"remaining_time":0.3930024429},
{"learn":[3.561173586],"iteration":673,"passed_time":0.8098839682,"remaining_time":0.3917242932},
{"learn":[3.559551904],"iteration":674,"passed_time":0.8108703436,"remaining_time":0.3904190543},
{"learn":[3.558593054],"iteration":675,"passed_time":0.8118630603,"remaining_time":0.3891177981},
{"learn":[3.555647008],"iteration":676,"passed_time":0.8128048463,"remaining_time":0.3877931541},
{"learn":[3.553100059],"iteration":677,"passed_time":0.8137838786,"remaining_time":0.3864873288},
{"learn":[3.55085578],"iteration":678,"passed_time":0.814774772,"remaining_time":0.3851880734},
{"learn":[3.550737965],"iteration":679,"passed_time":0.8156900509,"remaining_time":0.3838541416},
{"learn":[3.549408772],"iteration":680,"passed_time":0.8165601694,"remaining_time":0.3825002849},
{"learn":[3.547390589],"iteration":681,"passed_time":0.8174853458,"remaining_time":0.381173519},
{"learn":[3.54723575],"iteration":682,"passed_time":0.8183594113,"remaining_time":0.379824207},
{"learn":[3.543988891],"iteration":683,"passed_time":0.8192939044,"remaining_time":0.3785042014},
{"learn":[3.543868508],"iteration":684,"passed_time":0.8201863526,"remaining_time":0.377165987},
{"learn":[3.542752124],"iteration":685,"passed_time":0.8210265679,"remaining_time":0.3758051637},
{"learn":[3.541334315],"iteration":686,"passed_time":0.8219347441,"remaining_time":0.3744768194},
{"learn":[3.540208266],"iteration":687,"passed_time":0.8228357575,"remaining_time":0.3731464482},
{"learn":[3.537730983],"iteration":688,"passed_time":0.8237123576,"remaining_time":0.3718063036},
{"learn":[3.53419867],"iteration":689,"passed_time":0.8246377043,"remaining_time":0.3704894034},
{"learn":[3.532628335],"iteration":690,"passed_time":0.8255503385,"remaining_time":0.3691679516},
{"learn":[3.532204987],"iteration":691,"passed_time":0.826457543,"remaining_time":0.3678452648},
{"learn":[3.530618147],"iteration":692,"passed_time":0.8273584763,"remaining_time":0.3665209989},
{"learn":[3.528909306],"iteration":693,"passed_time":0.8282802467,"remaining_time":0.3652071405},
{"learn":[3.526700678],"iteration":694,"passed_time":0.8292021072,"remaining_time":0.3638944499},
{"learn":[3.526439574],"iteration":695,"passed_time":0.8300792482,"remaining_time":0.3625633498},
{"learn":[3.525784216],"iteration":696,"passed_time":0.8310073198,"remaining_time":0.3612556928},
{"learn":[3.524112693],"iteration":697,"passed_time":0.8319318351,"remaining_time":0.3599475848},
{"learn":[3.522813541],"iteration":698,"passed_time":0.8328609686,"remaining_time":0.358642563},
{"learn":[3.519148203],"iteration":699,"passed_time":0.8337363966,"remaining_time":0.3573155985},
{"learn":[3.517236747],"iteration":700,"passed_time":0.8346463259,"remaining_time":0.3560046383},
{"learn":[3.515603888],"iteration":701,"passed_time":0.835583083,"remaining_time":0.354706209},
{"learn":[3.51263524],"iteration":702,"passed_time":0.8365578677,"remaining_time":0.3534248744},
{"learn":[3.51123442],"iteration":703,"passed_time":0.8375018477,"remaining_time":0.3521314587},
{"learn":[3.50828027],"iteration":704,"passed_time":0.838416836,"remaining_time":0.350826903},
{"learn":[3.508265537],"iteration":705,"passed_time":0.8389689986,"remaining_time":0.3493723592},
{"learn":[3.506774876],"iteration":706,"passed_time":0.8398950567,"remaining_time":0.3480753205},
{"learn":[3.50552068],"iteration":707,"passed_time":0.8408592927,"remaining_time":0.3467950755},
{"learn":[3.501973993],"iteration":708,"passed_time":0.841821505,"remaining_time":0.3455148913},
{"learn":[3.498880354],"iteration":709,"passed_time":0.8427533934,"remaining_time":0.344223217},
{"learn":[3.497370959],"iteration":710,"passed_time":0.8436761155,"remaining_time":0.342928829},
{"learn":[3.496050455],"iteration":711,"passed_time":0.844588359,"remaining_time":0.3416312463},
{"learn":[3.495630067],"iteration":712,"passed_time":0.8454310587,"remaining_time":0.3403067515},
{"learn":[3.49550669],"iteration":713,"passed_time":0.8463084902,"remaining_time":0.3389975185},
{"learn":[3.493652375],"iteration":714,"passed_time":0.8472516486,"remaining_time":0.3377156921},
{"learn":[3.491915684],"iteration":715,"passed_time":0.8481299918,"remaining_time":0.3364091029},
{"learn":[3.490303956],"iteration":716,"passed_time":0.8491170183,"remaining_time":0.3351466056},
{"learn":[3.488363853],"iteration":717,"passed_time":0.8499772292,"remaining_time":0.3338350677},
{"learn":[3.485483936],"iteration":718,"passed_time":0.8511424929,"remaining_time":0.3326440063},
{"learn":[3.483763466],"iteration":719,"passed_time":0.8521567278,"remaining_time":0.331394283},
{"learn":[3.481642352],"iteration":720,"passed_time":0.8530820145,"remaining_time":0.3301107934},
{"learn":[3.479826119],"iteration":721,"passed_time":0.8540146142,"remaining_time":0.3288311118},
{"learn":[3.478588728],"iteration":722,"passed_time":0.8549676001,"remaining_time":0.3275602009},
{"learn":[3.475390887],"iteration":723,"passed_time":0.8560838066,"remaining_time":0.3263523903},
{"learn":[3.472636852],"iteration":724,"passed_time":0.8570091734,"remaining_time":0.3250724451},
{"learn":[3.47061883],"iteration":725,"passed_time":0.8579379262,"remaining_time":0.3237947545},
{"learn":[3.46953149],"iteration":726,"passed_time":0.8588418348,"remaining_time":0.3225086945},
{"learn":[3.467217162],"iteration":727,"passed_time":0.859842155,"remaining_time":0.3212597063},
{"learn":[3.465686216],"iteration":728,"passed_time":0.860762593,"remaining_time":0.3199817047},
{"learn":[3.462631216],"iteration":729,"passed_time":0.8616546506,"remaining_time":0.3186941858},
{"learn":[3.461451053],"iteration":730,"passed_time":0.8625215233,"remaining_time":0.3173984812},
{"learn":[3.458950469],"iteration":731,"passed_time":0.8634126992,"remaining_time":0.3161128462},
{"learn":[3.458072145],"iteration":732,"passed_time":0.864314975,"remaining_time":0.3148323306},
{"learn":[3.454364268],"iteration":733,"passed_time":0.8652756847,"remaining_time":0.313574022},
{"learn":[3.453243406],"iteration":734,"passed_time":0.8661917249,"remaining_time":0.3123004178},
{"learn":[3.453017963],"iteration":735,"passed_time":0.8671173321,"remaining_time":0.3110312169},
{"learn":[3.45201581],"iteration":736,"passed_time":0.8680577457,"remaining_time":0.3097682322},
{"learn":[3.449510107],"iteration":737,"passed_time":0.8689908162,"remaining_time":0.3085035147},
{"learn":[3.447189189],"iteration":738,"passed_time":0.8698963577,"remaining_time":0.3072299721},
{"learn":[3.446423605],"iteration":739,"passed_time":0.8707835866,"remaining_time":0.3059509899},
{"learn":[3.445531987],"iteration":740,"passed_time":0.8716724785,"remaining_time":0.3046736463},
{"learn":[3.445328199],"iteration":741,"passed_time":0.8725764673,"remaining_time":0.3034025991},
{"learn":[3.443327544],"iteration":742,"passed_time":0.8736352415,"remaining_time":0.3021860795},
{"learn":[3.441475798],"iteration":743,"passed_time":0.8746426944,"remaining_time":0.300952325},
{"learn":[3.439046501],"iteration":744,"passed_time":0.8756293002,"remaining_time":0.2997120423},
{"learn":[3.435899469],"iteration":745,"passed_time":0.876679058,"remaining_time":0.298493942},
{"learn":[3.433988352],"iteration":746,"passed_time":0.8776874225,"remaining_time":0.297262273},
{"learn":[3.433413263],"iteration":747,"passed_time":0.8786186097,"remaining_time":0.2960052001},
{"learn":[3.429944699],"iteration":748,"passed_time":0.8795534534,"remaining_time":0.2947502227},
{"learn":[3.429291634],"iteration":749,"passed_time":0.8805050368,"remaining_time":0.2935016789},
{"learn":[3.429175603],"iteration":750,"passed_time":0.8814239922,"remaining_time":0.2922431079},
{"learn":[3.428780323],"iteration":751,"passed_time":0.8823565719,"remaining_time":0.2909899333},
{"learn":[3.423893341],"iteration":752,"passed_time":0.8833393208,"remaining_time":0.2897540667},
{"learn":[3.421024316],"iteration":753,"passed_time":0.8843033464,"remaining_time":0.2885127629},
{"learn":[3.420969872],"iteration":754,"passed_time":0.885123546,"remaining_time":0.2872255216},
{"learn":[3.419544785],"iteration":755,"passed_time":0.8860228164,"remaining_time":0.285965036},
{"learn":[3.417057977],"iteration":756,"passed_time":0.8869051266,"remaining_time":0.2847000604},
{"learn":[3.415160245],"iteration":757,"passed_time":0.8877809152,"remaining_time":0.2834340125},
{"learn":[3.412854597],"iteration":758,"passed_time":0.8887548183,"remaining_time":0.2822001465},
{"learn":[3.410926347],"iteration":759,"passed_time":0.8896979768,"remaining_time":0.2809572558},
{"learn":[3.408963843],"iteration":760,"passed_time":0.8906076357,"remaining_time":0.279704632},
{"learn":[3.407629634],"iteration":761,"passed_time":0.8915919373,"remaining_time":0.2784762219},
{"learn":[3.404384724],"iteration":762,"passed_time":0.8925018066,"remaining_time":0.2772253318},
{"learn":[3.403041656],"iteration":763,"passed_time":0.893432583,"remaining_time":0.2759817927},
{"learn":[3.401101731],"iteration":764,"passed_time":0.8943151336,"remaining_time":0.2747242567},
{"learn":[3.400890668],"iteration":765,"passed_time":0.8952380761,"remaining_time":0.2734800389},
{"learn":[3.399289941],"iteration":766,"passed_time":0.8961369758,"remaining_time":0.2722293551},
{"learn":[3.399202366],"iteration":767,"passed_time":0.8970486883,"remaining_time":0.2709834579},
{"learn":[3.397447845],"iteration":768,"passed_time":0.8979876393,"remaining_time":0.2697466121},
{"learn":[3.394655341],"iteration":769,"passed_time":0.8989439111,"remaining_time":0.2685157137},
{"learn":[3.393228229],"iteration":770,"passed_time":0.8999515042,"remaining_time":0.267300771},
{"learn":[3.389691197],"iteration":771,"passed_time":0.9009360764,"remaining_time":0.2660795666},
{"learn":[3.389626772],"iteration":772,"passed_time":0.9018335435,"remaining_time":0.2648333951},
{"learn":[3.388480222],"iteration":773,"passed_time":0.902776672,"remaining_time":0.2636014572},
{"learn":[3.388215066],"iteration":774,"passed_time":0.9037299585,"remaining_time":0.2623732137},
{"learn":[3.386324358],"iteration":775,"passed_time":0.9046830646,"remaining_time":0.2611456269},
{"learn":[3.383913061],"iteration":776,"passed_time":0.9057270024,"remaining_time":0.2599448154},
{"learn":[3.382839768],"iteration":777,"passed_time":0.906694364,"remaining_time":0.2587225563},
{"learn":[3.381961844],"iteration":778,"passed_time":0.9075482636,"remaining_time":0.2574687628},
{"learn":[3.381521703],"iteration":779,"passed_time":0.9084501486,"remaining_time":0.2562295291},
{"learn":[3.380918963],"iteration":780,"passed_time":0.9093638046,"remaining_time":0.2549944599},
{"learn":[3.377139006],"iteration":781,"passed_time":0.9102998905,"remaining_time":0.2537664656},
{"learn":[3.376004372],"iteration":782,"passed_time":0.9111943623,"remaining_time":0.2525276841},
{"learn":[3.373826468],"iteration":783,"passed_time":0.9121169441,"remaining_time":0.2512975254},
{"learn":[3.373546786],"iteration":784,"passed_time":0.9129824344,"remaining_time":0.2500525139},
{"learn":[3.372109181],"iteration":785,"passed_time":0.913944797,"remaining_time":0.248834843},
{"learn":[3.370764924],"iteration":786,"passed_time":0.9149007182,"remaining_time":0.2476160775},
{"learn":[3.367833107],"iteration":787,"passed_time":0.9157848516,"remaining_time":0.2463786657},
{"learn":[3.36450404],"iteration":788,"passed_time":0.9167916734,"remaining_time":0.2451749596},
{"learn":[3.361794558],"iteration":789,"passed_time":0.9177057501,"remaining_time":0.2439470981},
{"learn":[3.356880529],"iteration":790,"passed_time":0.9186309566,"remaining_time":0.2427229708},
{"learn":[3.353843509],"iteration":791,"passed_time":0.9195827805,"remaining_time":0.2415065888},
{"learn":[3.353640253],"iteration":792,"passed_time":0.9204956952,"remaining_time":0.2402807174},
{"learn":[3.353055088],"iteration":793,"passed_time":0.9213908282,"remaining_time":0.2390510209},
{"learn":[3.351415617],"iteration":794,"passed_time":0.9222687606,"remaining_time":0.2378177307},
{"learn":[3.349169061],"iteration":795,"passed_time":0.9231541262,"remaining_time":0.2365872384},
{"learn":[3.346211014],"iteration":796,"passed_time":0.9241045876,"remaining_time":0.2353741923},
{"learn":[3.344560452],"iteration":797,"passed_time":0.925098827,"remaining_time":0.234172886},
{"learn":[3.344445461],"iteration":798,"passed_time":0.9260024151,"remaining_time":0.2329492934},
{"learn":[3.342608898],"iteration":799,"passed_time":0.9270108397,"remaining_time":0.2317527099},
{"learn":[3.339572899],"iteration":800,"passed_time":0.9279836309,"remaining_time":0.2305477435},
{"learn":[3.339309302],"iteration":801,"passed_time":0.9288860168,"remaining_time":0.2293259742},
{"learn":[3.33698088],"iteration":802,"passed_time":0.9298324511,"remaining_time":0.2281158068},
{"learn":[3.334746342],"iteration":803,"passed_time":0.9307357386,"remaining_time":0.2268957771},
{"learn":[3.332048511],"iteration":804,"passed_time":0.9316614861,"remaining_time":0.2256819749},
{"learn":[3.331932544],"iteration":805,"passed_time":0.9325764844,"remaining_time":0.2244663002},
{"learn":[3.330541133],"iteration":806,"passed_time":0.9335204543,"remaining_time":0.2232582995},
{"learn":[3.329124989],"iteration":807,"passed_time":0.9344689723,"remaining_time":0.222052033},
{"learn":[3.32583918],"iteration":808,"passed_time":0.935347055,"remaining_time":0.2208297744},
{"learn":[3.325287299],"iteration":809,"passed_time":0.936270258,"remaining_time":0.2196189494},
{"learn":[3.322745162],"iteration":810,"passed_time":0.937224436,"remaining_time":0.2184160523},
{"learn":[3.319733662],"iteration":811,"passed_time":0.9381841139,"remaining_time":0.2172150411},
{"learn":[3.318080007],"iteration":812,"passed_time":0.9391142792,"remaining_time":0.2160078354},
{"learn":[3.317179538],"iteration":813,"passed_time":0.9400518678,"remaining_time":0.2148030066},
{"learn":[3.315685949],"iteration":814,"passed_time":0.9409242403,"remaining_time":0.21358403},
{"learn":[3.314944576],"iteration":815,"passed_time":0.9418028238,"remaining_time":0.2123673034},
{"learn":[3.312369052],"iteration":816,"passed_time":0.9427635636,"remaining_time":0.2111698068},
{"learn":[3.312321621],"iteration":817,"passed_time":0.9434724151,"remaining_time":0.2099168454},
{"learn":[3.309465776],"iteration":818,"passed_time":0.9444707918,"remaining_time":0.2087291982},
{"learn":[3.308307377],"iteration":819,"passed_time":0.9454668645,"remaining_time":0.2075415068},
{"learn":[3.308076804],"iteration":820,"passed_time":0.9463940846,"remaining_time":0.2063392706},
{"learn":[3.305643326],"iteration":821,"passed_time":0.9473160653,"remaining_time":0.2051365689},
{"learn":[3.304154814],"iteration":822,"passed_time":0.948272848,"remaining_time":0.2039420341},
{"learn":[3.303076321],"iteration":823,"passed_time":0.9491689327,"remaining_time":0.2027351118},
{"learn":[3.301746372],"iteration":824,"passed_time":0.9500220209,"remaining_time":0.2015198226},
{"learn":[3.301345455],"iteration":825,"passed_time":0.9509281936,"remaining_time":0.2003165928},
{"learn":[3.299181039],"iteration":826,"passed_time":0.9518253702,"remaining_time":0.1991121996},
{"learn":[3.297989357],"iteration":827,"passed_time":0.9526516507,"remaining_time":0.1978938212},
{"learn":[3.294775182],"iteration":828,"passed_time":0.9535570119,"remaining_time":0.1966927009},
{"learn":[3.293840636],"iteration":829,"passed_time":0.9544495903,"remaining_time":0.1954896751},
{"learn":[3.289279397],"iteration":830,"passed_time":0.955454649,"remaining_time":0.1943102716},
{"learn":[3.286204979],"iteration":831,"passed_time":0.9563876794,"remaining_time":0.193116743},
{"learn":[3.284833593],"iteration":832,"passed_time":0.9572800976,"remaining_time":0.1919156978},
{"learn":[3.283519914],"iteration":833,"passed_time":0.9582284653,"remaining_time":0.1907265291},
{"learn":[3.282853026],"iteration":834,"passed_time":0.959159392,"remaining_time":0.1895344906},
{"learn":[3.281944673],"iteration":835,"passed_time":0.960101158,"remaining_time":0.1883452032},
{"learn":[3.279764865],"iteration":836,"passed_time":0.9610748508,"remaining_time":0.1871627248},
{"learn":[3.277468839],"iteration":837,"passed_time":0.9619375461,"remaining_time":0.1859592869},
{"learn":[3.277124974],"iteration":838,"passed_time":0.9628594367,"remaining_time":0.1847680206},
{"learn":[3.275636037],"iteration":839,"passed_time":0.9637776708,"remaining_time":0.1835766992},
{"learn":[3.274413635],"iteration":840,"passed_time":0.964633023,"remaining_time":0.1823741387},
{"learn":[3.272636087],"iteration":841,"passed_time":0.9655339163,"remaining_time":0.1811809487},
{"learn":[3.269644466],"iteration":842,"passed_time":0.9665068076,"remaining_time":0.180001861},
{"learn":[3.26852083],"iteration":843,"passed_time":0.9674751509,"remaining_time":0.1788224213},
{"learn":[3.267820927],"iteration":844,"passed_time":0.9683454798,"remaining_time":0.1776255022},
{"learn":[3.267331099],"iteration":845,"passed_time":0.969257032,"remaining_time":0.1764368593},
{"learn":[3.267231014],"iteration":846,"passed_time":0.9701501514,"remaining_time":0.1752455409},
{"learn":[3.267158695],"iteration":847,"passed_time":0.971009661,"remaining_time":0.1740489015},
{"learn":[3.264718705],"iteration":848,"passed_time":0.9719939427,"remaining_time":0.1728752478},
{"learn":[3.261678512],"iteration":849,"passed_time":0.9730668521,"remaining_time":0.1717176798},
{"learn":[3.261368381],"iteration":850,"passed_time":0.9739809588,"remaining_time":0.1705325063},
{"learn":[3.260128799],"iteration":851,"passed_time":0.9748444255,"remaining_time":0.1693391725},
{"learn":[3.258972952],"iteration":852,"passed_time":0.9757857306,"remaining_time":0.1681600263},
{"learn":[3.258724846],"iteration":853,"passed_time":0.9767232591,"remaining_time":0.1669807914},
{"learn":[3.25686724],"iteration":854,"passed_time":0.9776045474,"remaining_time":0.1657925841},
{"learn":[3.255750259],"iteration":855,"passed_time":0.9784530675,"remaining_time":0.1645995814},
{"learn":[3.254915866],"iteration":856,"passed_time":0.9793555035,"remaining_time":0.1634163792},
{"learn":[3.254348625],"iteration":857,"passed_time":0.9802613155,"remaining_time":0.1622343902},
{"learn":[3.253408514],"iteration":858,"passed_time":0.9811552464,"remaining_time":0.161051094},
{"learn":[3.253291714],"iteration":859,"passed_time":0.9820565203,"remaining_time":0.1598696661},
{"learn":[3.250186342],"iteration":860,"passed_time":0.9829570128,"remaining_time":0.1586887628},
{"learn":[3.249141318],"iteration":861,"passed_time":0.983873604,"remaining_time":0.1575110874},
{"learn":[3.246300388],"iteration":862,"passed_time":0.9848603601,"remaining_time":0.1563451557},
{"learn":[3.245205135],"iteration":863,"passed_time":0.985777923,"remaining_time":0.1551687471},
{"learn":[3.244403535],"iteration":864,"passed_time":0.9866979202,"remaining_time":0.153993317},
{"learn":[3.244211781],"iteration":865,"passed_time":0.9876274344,"remaining_time":0.1528199494},
{"learn":[3.242286347],"iteration":866,"passed_time":0.9885508477,"remaining_time":0.1516462085},
{"learn":[3.239606746],"iteration":867,"passed_time":0.9894722074,"remaining_time":0.150472732},
{"learn":[3.236773361],"iteration":868,"passed_time":0.9903885482,"remaining_time":0.1492990792},
{"learn":[3.234552446],"iteration":869,"passed_time":0.9913316666,"remaining_time":0.1481300191},
{"learn":[3.233724647],"iteration":870,"passed_time":0.9922575342,"remaining_time":0.146958923},
{"learn":[3.230851485],"iteration":871,"passed_time":0.9931303776,"remaining_time":0.1457806059},
{"learn":[3.227728941],"iteration":872,"passed_time":0.9940537909,"remaining_time":0.1446103453},
{"learn":[3.225787575],"iteration":873,"passed_time":0.9949701317,"remaining_time":0.14343963},
{"learn":[3.222797487],"iteration":874,"passed_time":0.9958401099,"remaining_time":0.1422628728},
{"learn":[3.22137014],"iteration":875,"passed_time":0.9967598968,"remaining_time":0.1410938667},
{"learn":[3.219701963],"iteration":876,"passed_time":0.9977281499,"remaining_time":0.1399322263},
{"learn":[3.21783327],"iteration":877,"passed_time":0.9987551275,"remaining_time":0.1387791863},
{"learn":[3.217713355],"iteration":878,"passed_time":0.9996690439,"remaining_time":0.1376108695},
{"learn":[3.217666091],"iteration":879,"passed_time":1.00054367,"remaining_time":0.1364377732},
{"learn":[3.214962005],"iteration":880,"passed_time":1.001428305,"remaining_time":0.1352667063},
{"learn":[3.214081828],"iteration":881,"passed_time":1.002381812,"remaining_time":0.1341055031},
{"learn":[3.213358337],"iteration":882,"passed_time":1.003355855,"remaining_time":0.1329474916},
{"learn":[3.210850401],"iteration":883,"passed_time":1.004262909,"remaining_time":0.1317811057},
{"learn":[3.207810328],"iteration":884,"passed_time":1.00513441,"remaining_time":0.1306106861},
{"learn":[3.204935073],"iteration":885,"passed_time":1.00611156,"remaining_time":0.1294545348},
{"learn":[3.20280198],"iteration":886,"passed_time":1.007058475,"remaining_time":0.1282949353},
{"learn":[3.200663495],"iteration":887,"passed_time":1.008005861,"remaining_time":0.1271358743},
{"learn":[3.197301669],"iteration":888,"passed_time":1.008933742,"remaining_time":0.1259748542},
{"learn":[3.195666943],"iteration":889,"passed_time":1.009805563,"remaining_time":0.1248074292},
{"learn":[3.193886506],"iteration":890,"passed_time":1.010719941,"remaining_time":0.1236458738},
{"learn":[3.190601248],"iteration":891,"passed_time":1.01164119,"remaining_time":0.1224857046},
{"learn":[3.188983797],"iteration":892,"passed_time":1.012533689,"remaining_time":0.1213226256},
{"learn":[3.187365749],"iteration":893,"passed_time":1.013415889,"remaining_time":0.1201589309},
{"learn":[3.186160771],"iteration":894,"passed_time":1.014351494,"remaining_time":0.1190021305},
{"learn":[3.185358981],"iteration":895,"passed_time":1.015193312,"remaining_time":0.117834938},
{"learn":[3.183832164],"iteration":896,"passed_time":1.016117697,"remaining_time":0.1166779518},
{"learn":[3.183106966],"iteration":897,"passed_time":1.017030231,"remaining_time":0.1155201376},
{"learn":[3.182838152],"iteration":898,"passed_time":1.017858635,"remaining_time":0.1143534173},
{"learn":[3.180835453],"iteration":899,"passed_time":1.018753027,"remaining_time":0.1131947807},
{"learn":[3.179957348],"iteration":900,"passed_time":1.01965947,"remaining_time":0.1120380549},
{"learn":[3.179752966],"iteration":901,"passed_time":1.020563248,"remaining_time":0.1108815946},
{"learn":[3.178851983],"iteration":902,"passed_time":1.021531541,"remaining_time":0.109732624},
{"learn":[3.176748586],"iteration":903,"passed_time":1.0224019,"remaining_time":0.1085736531},
{"learn":[3.172960988],"iteration":904,"passed_time":1.023394867,"remaining_time":0.1074281905},
{"learn":[3.172794225],"iteration":905,"passed_time":1.02431248,"remaining_time":0.1062752463},
{"learn":[3.169996507],"iteration":906,"passed_time":1.025261309,"remaining_time":0.1051260218},
{"learn":[3.16813015],"iteration":907,"passed_time":1.026167882,"remaining_time":0.1039729572},
{"learn":[3.166920871],"iteration":908,"passed_time":1.027104509,"remaining_time":0.1028234437},
{"learn":[3.16531606],"iteration":909,"passed_time":1.028020419,"remaining_time":0.1016723491},
{"learn":[3.162035247],"iteration":910,"passed_time":1.028894605,"remaining_time":0.1005176947},
{"learn":[3.16189467],"iteration":911,"passed_time":1.029772818,"remaining_time":0.09936404381},
{"learn":[3.161008416],"iteration":912,"passed_time":1.030713993,"remaining_time":0.09821699601},
{"learn":[3.160560787],"iteration":913,"passed_time":1.031626897,"remaining_time":0.09706773869},
{"learn":[3.160416261],"iteration":914,"passed_time":1.032541425,"remaining_time":0.09591914875},
{"learn":[3.15844291],"iteration":915,"passed_time":1.033419047,"remaining_time":0.0947676855},
{"learn":[3.155040501],"iteration":916,"passed_time":1.034317716,"remaining_time":0.09361872456},
{"learn":[3.154937548],"iteration":917,"passed_time":1.035308859,"remaining_time":0.09247856914},
{"learn":[3.153721161],"iteration":918,"passed_time":1.03631477,"remaining_time":0.09134003954},
{"learn":[3.153170511],"iteration":919,"passed_time":1.037302347,"remaining_time":0.09020020409},
{"learn":[3.153113601],"iteration":920,"passed_time":1.038258018,"remaining_time":0.08905796244},
{"learn":[3.150607379],"iteration":921,"passed_time":1.039330617,"remaining_time":0.08792601749},
{"learn":[3.148408359],"iteration":922,"passed_time":1.04033285,"remaining_time":0.08678833095},
{"learn":[3.147495728],"iteration":923,"passed_time":1.041367031,"remaining_time":0.08565356529},
{"learn":[3.146946235],"iteration":924,"passed_time":1.042357473,"remaining_time":0.08451547081},
{"learn":[3.14472738],"iteration":925,"passed_time":1.043325506,"remaining_time":0.08337590437},
{"learn":[3.144469477],"iteration":926,"passed_time":1.044259208,"remaining_time":0.08223400449},
{"learn":[3.142975516],"iteration":927,"passed_time":1.045258396,"remaining_time":0.08109763416},
{"learn":[3.14079113],"iteration":928,"passed_time":1.046191526,"remaining_time":0.07995651063},
{"learn":[3.138173032],"iteration":929,"passed_time":1.047155622,"remaining_time":0.07881816511},
{"learn":[3.136352813],"iteration":930,"passed_time":1.048010023,"remaining_time":0.07767206398},
{"learn":[3.133735004],"iteration":931,"passed_time":1.048903843,"remaining_time":0.07652946497},
{"learn":[3.1319496],"iteration":932,"passed_time":1.049878989,"remaining_time":0.07539323928},
{"learn":[3.129865343],"iteration":933,"passed_time":1.050758424,"remaining_time":0.07425059526},
{"learn":[3.129830206],"iteration":934,"passed_time":1.051476862,"remaining_time":0.07309732198},
{"learn":[3.126676562],"iteration":935,"passed_time":1.052372917,"remaining_time":0.07195712253},
{"learn":[3.12645665],"iteration":936,"passed_time":1.053275583,"remaining_time":0.07081788875},
{"learn":[3.126378007],"iteration":937,"passed_time":1.05418381,"remaining_time":0.06967952687},
{"learn":[3.124621914],"iteration":938,"passed_time":1.055105179,"remaining_time":0.06854250899},
{"learn":[3.123379018],"iteration":939,"passed_time":1.056081016,"remaining_time":0.06740942658},
{"learn":[3.123332451],"iteration":940,"passed_time":1.05693139,"remaining_time":0.0662688119},
{"learn":[3.122432444],"iteration":941,"passed_time":1.057911153,"remaining_time":0.06513678014},
{"learn":[3.121889006],"iteration":942,"passed_time":1.058861144,"remaining_time":0.06400327169},
{"learn":[3.121070914],"iteration":943,"passed_time":1.059727846,"remaining_time":0.06286521123},
{"learn":[3.118444705],"iteration":944,"passed_time":1.060638267,"remaining_time":0.06173026948},
{"learn":[3.116820458],"iteration":945,"passed_time":1.061549528,"remaining_time":0.06059585045},
{"learn":[3.114971041],"iteration":946,"passed_time":1.062459387,"remaining_time":0.05946182422},
{"learn":[3.114685138],"iteration":947,"passed_time":1.063506245,"remaining_time":0.05833578559},
{"learn":[3.113399363],"iteration":948,"passed_time":1.064586253,"remaining_time":0.05721169534},
{"learn":[3.110575399],"iteration":949,"passed_time":1.065601429,"remaining_time":0.05608428574},
{"learn":[3.110466553],"iteration":950,"passed_time":1.06654567,"remaining_time":0.05495345721},
{"learn":[3.108691641],"iteration":951,"passed_time":1.067427288,"remaining_time":0.05381986329},
{"learn":[3.107898017],"iteration":952,"passed_time":1.068282881,"remaining_time":0.0526855146},
{"learn":[3.105551729],"iteration":953,"passed_time":1.069223485,"remaining_time":0.05155584938},
{"learn":[3.104824945],"iteration":954,"passed_time":1.070139145,"remaining_time":0.05042540472},
{"learn":[3.103186704],"iteration":955,"passed_time":1.071035149,"remaining_time":0.04929450477},
{"learn":[3.102330655],"iteration":956,"passed_time":1.07192915,"remaining_time":0.0481640057},
{"learn":[3.102291298],"iteration":957,"passed_time":1.072823051,"remaining_time":0.04703399597},
{"learn":[3.100363529],"iteration":958,"passed_time":1.073723413,"remaining_time":0.04590475489},
{"learn":[3.097871596],"iteration":959,"passed_time":1.07463766,"remaining_time":0.04477656918},
{"learn":[3.097372213],"iteration":960,"passed_time":1.075536059,"remaining_time":0.04364818554},
{"learn":[3.095981813],"iteration":961,"passed_time":1.076464992,"remaining_time":0.04252148618},
{"learn":[3.095347452],"iteration":962,"passed_time":1.077335461,"remaining_time":0.04139295127},
{"learn":[3.094728409],"iteration":963,"passed_time":1.07825637,"remaining_time":0.0402668354},
{"learn":[3.094118537],"iteration":964,"passed_time":1.079165759,"remaining_time":0.03914072699},
{"learn":[3.093793695],"iteration":965,"passed_time":1.080069276,"remaining_time":0.03801486066},
{"learn":[3.092581602],"iteration":966,"passed_time":1.080941929,"remaining_time":0.0368884009},
{"learn":[3.091694202],"iteration":967,"passed_time":1.08186935,"remaining_time":0.03576427603},
{"learn":[3.090298312],"iteration":968,"passed_time":1.082775302,"remaining_time":0.03463987035},
{"learn":[3.090020107],"iteration":969,"passed_time":1.083655829,"remaining_time":0.03351512874},
{"learn":[3.088949869],"iteration":970,"passed_time":1.084606653,"remaining_time":0.03239298964},
{"learn":[3.086700204],"iteration":971,"passed_time":1.08560511,"remaining_time":0.03127257518},
{"learn":[3.086584317],"iteration":972,"passed_time":1.086494753,"remaining_time":0.03014939192},
{"learn":[3.084850742],"iteration":973,"passed_time":1.087395957,"remaining_time":0.0290269968},
{"learn":[3.084239948],"iteration":974,"passed_time":1.088346589,"remaining_time":0.02790632279},
{"learn":[3.082561673],"iteration":975,"passed_time":1.08926868,"remaining_time":0.0267852954},
{"learn":[3.07991814],"iteration":976,"passed_time":1.09016225,"remaining_time":0.02566400384},
{"learn":[3.079350277],"iteration":977,"passed_time":1.091070877,"remaining_time":0.02454351666},
{"learn":[3.077637462],"iteration":978,"passed_time":1.092008253,"remaining_time":0.02342407898},
{"learn":[3.076733301],"iteration":979,"passed_time":1.092887278,"remaining_time":0.02230382199},
{"learn":[3.07594065],"iteration":980,"passed_time":1.093757516,"remaining_time":0.02118388666},
{"learn":[3.072594655],"iteration":981,"passed_time":1.094653661,"remaining_time":0.02006493473},
{"learn":[3.071977674],"iteration":982,"passed_time":1.095601258,"remaining_time":0.01894732592},
{"learn":[3.069532634],"iteration":983,"passed_time":1.096479881,"remaining_time":0.01782894116},
{"learn":[3.068870784],"iteration":984,"passed_time":1.097328962,"remaining_time":0.01671059333},
{"learn":[3.068801463],"iteration":985,"passed_time":1.09820446,"remaining_time":0.01559316678},
{"learn":[3.067433249],"iteration":986,"passed_time":1.099104232,"remaining_time":0.01447655016},
{"learn":[3.065611456],"iteration":987,"passed_time":1.099981964,"remaining_time":0.01336010482},
{"learn":[3.063039162],"iteration":988,"passed_time":1.10085644,"remaining_time":0.012244106},
{"learn":[3.06177873],"iteration":989,"passed_time":1.101779022,"remaining_time":0.01112908103},
{"learn":[3.061689148],"iteration":990,"passed_time":1.102657705,"remaining_time":0.01001404576},
{"learn":[3.058984039],"iteration":991,"passed_time":1.103608868,"remaining_time":0.008900071517},
{"learn":[3.057492984],"iteration":992,"passed_time":1.104468899,"remaining_time":0.00778578277},
{"learn":[3.057290731],"iteration":993,"passed_time":1.105401478,"remaining_time":0.006672443531},
{"learn":[3.056068348],"iteration":994,"passed_time":1.106464993,"remaining_time":0.005560125591},
{"learn":[3.054987307],"iteration":995,"passed_time":1.107366567,"remaining_time":0.00444725529},
{"learn":[3.054200234],"iteration":996,"passed_time":1.108276446,"remaining_time":0.003334833841},
{"learn":[3.052732869],"iteration":997,"passed_time":1.109172932,"remaining_time":0.002222791446},
{"learn":[3.051787862],"iteration":998,"passed_time":1.110157717,"remaining_time":0.001111268986},
{"learn":[3.051366222],"iteration":999,"passed_time":1.111080198,"remaining_time":0}
]}